{
  "pane1": [
    {
      "title": "[속보] 송성문 ML 첫 안타→역전 2타점 2루타! 사이영상 2위 우완 무너트...",
      "originallink": "https://www.starnewskorea.com/sports/2026/05/06/2026050611422864820",
      "link": "https://m.sports.naver.com/wbaseball/article/108/0003433085",
      "description": "샌디에이고 파드리스 송성문(30)이 내셔널리그 사이영상 2위 투수를 상대로 메이저리그 첫 안타를 터트렸다. 송성문은 6일(한국시간) 미국 캘리포니아주 샌프란시스코의 오라클 파크에서 열린 2026 미국프로야구... ",
      "pubDate": "Wed, 06 May 2026 11:57:00 +0900",
      "formatted_date": "05월 06일, 11시 57분",
      "ai_summary": "샌디에이고 파드리스 송성문이 내셔널리그 사이영상 2위 투수를 상대로 메이저리그 첫 안타를 역전 2타점 2루타로 장식했다."
    },
    {
      "title": "[속보] 송성문 해냈다! 빅리그 첫 선발서 '역전 2타점 적시타' 폭발→이...",
      "originallink": "https://www.xportsnews.com/article/2145265",
      "link": "https://m.sports.naver.com/wbaseball/article/311/0002007452",
      "description": "미국 메이저리그(MLB)에서 생애 첫 선발 출장 경기를 치르는 중인 한국인 내야수 송성문(29)이 첫 안타를 역전 적시타로 터뜨리며 강렬한 첫인상을 남겼다. 송성문의 소속팀 샌디에이고 파드리스는 6일(한국시간) 미국... ",
      "pubDate": "Wed, 06 May 2026 11:54:00 +0900",
      "formatted_date": "05월 06일, 11시 54분",
      "ai_summary": "MLB 생애 첫 선발 출장 경기에 나선 송성문이 역전 2타점 적시타를 터뜨리며 강렬한 데뷔전을 치렀다."
    },
    {
      "title": "[속보] 경악! '독 품은' 송성문, 샌프란시스코 향해 독침 쐈다! 美 대표...",
      "originallink": "https://www.sportalkorea.com/news/articleView.html?idxno=2025052909553193092",
      "link": "https://m.sports.naver.com/wbaseball/article/139/0002246762",
      "description": "마이너리그에서 생활하며 이를 갈고 독을 품었던 송성문(샌디에이고 파드리스)이 메이저리그 2번째 경기만에 결정적인 적시타를 날렸다. 송성문은 6일(이하 한국시간) 미국 캘리포니아주 샌프란시스코 오라클... ",
      "pubDate": "Wed, 06 May 2026 11:50:00 +0900",
      "formatted_date": "05월 06일, 11시 50분",
      "ai_summary": "마이너리그 생활 끝에 메이저리그에 콜업된 송성문이 두 번째 경기 만에 팀 승리를 이끄는 결정적인 적시타를 기록했다."
    },
    {
      "title": "[속보] 민주, 군산·김제·부안을 보궐선거 박지원 최고 공천",
      "originallink": "https://www.jjan.kr/article/20260506500103",
      "link": "https://www.jjan.kr/article/20260506500103",
      "description": "박지원 평당원 최고위원. / 연합뉴스 제공 /유민성 ok2ws9@naver.com /유민성",
      "pubDate": "Wed, 06 May 2026 11:48:00 +0900",
      "formatted_date": "05월 06일, 11시 48분",
      "ai_summary": "더불어민주당이 군산·김제·부안 보궐선거 후보로 박지원 최고위원을 공천했다."
    },
    {
      "title": "[속보] 송성문 미쳤다, 2타점 역전 2루타로 ML 데뷔 첫 안타 완성→타점...",
      "originallink": "https://www.mydaily.co.kr/page/view/2026050611433624273",
      "link": "https://m.sports.naver.com/wbaseball/article/117/0004061523",
      "description": "송성문(샌디에이고 파드리스)이 빅리그 두 타석만에 데뷔 첫 안타를 신고했다. 송성문은 6일(한국시각) 미국 캘리포니아주 샌프란시스코의 오라클 파크에서 열린 2026 메이저리그 샌프란시스코 자이언츠와 경기서 9번... ",
      "pubDate": "Wed, 06 May 2026 11:47:00 +0900",
      "formatted_date": "05월 06일, 11시 47분",
      "ai_summary": "송성문이 샌프란시스코와의 경기에서 빅리그 데뷔 첫 안타를 2타점 역전 2루타로 기록하며 화려하게 신고했다."
    },
    {
      "title": "[속보] '미쳤다' 송성문 ML 데뷔 첫 안타 터졌다! 2타점 2루타 폭발...ML...",
      "originallink": "http://www.osen.co.kr/article/G1112795513",
      "link": "https://m.sports.naver.com/wbaseball/article/109/0005528176",
      "description": "샌디에이고 파드리스 송성문이 콜업에 이어 동시에 데뷔 첫 선발 출장 기회까지 잡았고 결정적 순간 첫 안타 타점 득점을 모두 달성했다. 송성문은 6일(이하 한국시간) 미국 캘리포니아주 샌프란시스코 오라클... ",
      "pubDate": "Wed, 06 May 2026 11:46:00 +0900",
      "formatted_date": "05월 06일, 11시 46분",
      "ai_summary": "콜업과 동시에 첫 선발 출전 기회를 잡은 송성문이 데뷔 첫 안타와 타점, 득점을 모두 달성하며 맹활약했다."
    },
    {
      "title": "[속보] HMM &quot;나무호, 당시 이란 통제선 밖 정박...단독 항행 어려워&quot;",
      "originallink": "https://www.ytn.co.kr/_ln/0102_202605061144205050",
      "link": "https://n.news.naver.com/mnews/article/052/0002349301?sid=101",
      "description": "호르무즈 해협에서 폭발·화재 사고가 난 나무호의 선사, HMM은 당시 선박이 이란의 통제선 밖에 정박하고 있었다고 밝혔습니다. HMM 관계자는 YTN과의 통화에서 사고가 발생한 지난 4일 이란이 호르무즈 해협 통제 구역을... ",
      "pubDate": "Wed, 06 May 2026 11:44:00 +0900",
      "formatted_date": "05월 06일, 11시 44분",
      "ai_summary": "HMM은 호르무즈 해협에서 사고가 난 나무호가 당시 이란 통제선 밖에서 정박 중이었으며 단독 항행은 어려웠다고 해명했다."
    },
    {
      "title": "[속보] 송성문 ML 데뷔 첫 2루타·타점·득점 폭발",
      "originallink": "https://www.spotvnews.co.kr/news/articleView.html?idxno=814895",
      "link": "https://m.sports.naver.com/wbaseball/article/477/0000607128",
      "description": "송성문에 메이저리그 첫 선발 데뷔 경기에서 안타와 타점을 터뜨렸다. 6일(한국시간) 미국 캘리포니아주 샌프란시스코 오라클파크에서 열린 2026 메이저리그 샌프란시스코 자이언츠와 경기에 9번 타자 2루수로 선발... ",
      "pubDate": "Wed, 06 May 2026 11:42:00 +0900",
      "formatted_date": "05월 06일, 11시 42분",
      "ai_summary": "송성문이 메이저리그 첫 선발 데뷔전에서 2루타와 타점, 득점을 모두 기록하며 팀 공격을 이끌었다."
    },
    {
      "title": "[속보]호르무즈 봉쇄 후 세 번째 한국 유조선 홍해 통과",
      "originallink": "https://www.ichannela.com/news/main/news_detailPage.do?publishId=000000527621",
      "link": "https://n.news.naver.com/mnews/article/449/0000344159?sid=104",
      "description": "이란 호르무즈 해협 봉쇄 이후 우리 유조선이 추가로 원유 수송 우회로인 홍해를 안전하게 통과한 것으로 알려졌습니다. 호르무즈 해협 봉쇄 후 한국 선박이 홍해를 통과한 것은 이번이 3번째입니다. 해양수산부는 6일... ",
      "pubDate": "Wed, 06 May 2026 11:41:00 +0900",
      "formatted_date": "05월 06일, 11시 41분",
      "ai_summary": "이란의 호르무즈 해협 봉쇄 이후 우리 유조선이 세 번째로 홍해 우회로를 안전하게 통과했다."
    },
    {
      "title": "[속보] 삼성전자 '시가총액 1조달러 클럽' 입성…아시아서 2번째",
      "originallink": "https://economist.co.kr/article/view/ecn202605060018",
      "link": "https://n.news.naver.com/mnews/article/243/0000097474?sid=004",
      "description": "삼성전자 '시가총액 1조달러 클럽' 입성…아시아서 2번째",
      "pubDate": "Wed, 06 May 2026 11:40:00 +0900",
      "formatted_date": "05월 06일, 11시 40분",
      "ai_summary": "삼성전자가 시가총액 1조 달러를 돌파하며 아시아 기업으로는 두 번째로 '1조 달러 클럽'에 입성했다."
    },
    {
      "title": "[속보] 파두, 500억원 규모 기업용 SSD 컨트롤러 공급계약 체결",
      "originallink": "https://www.cbci.co.kr/news/articleView.html?idxno=572513",
      "link": "https://www.cbci.co.kr/news/articleView.html?idxno=572513",
      "description": "파두 로고. 홈페이지 캡처 [단박에 - CBC뉴스 | CBCNEWS] 파두는 해외 낸드플래시 메모리 제조사와 기업용 SSD 컨트롤러 공급 계약을 체결했다고 6일 공시했다. 계약금액은 500억1170만5000원으로, 최근 매출액... ",
      "pubDate": "Wed, 06 May 2026 11:40:00 +0900",
      "formatted_date": "05월 06일, 11시 40분",
      "ai_summary": "파두가 해외 낸드플래시 제조사와 500억 원 규모의 기업용 SSD 컨트롤러 공급 계약을 체결했습니다. 이번 계약으로 매출 확대가 기대됩니다."
    },
    {
      "title": "[속보]송성문, MLB 데뷔 첫 안타 폭발…2루타 작렬",
      "originallink": "https://www.newsis.com/view/NISX20260506_0003618288",
      "link": "https://m.sports.naver.com/wbaseball/article/003/0013927911",
      "description": "",
      "pubDate": "Wed, 06 May 2026 11:39:00 +0900",
      "formatted_date": "05월 06일, 11시 39분",
      "ai_summary": "송성문 선수가 MLB 데뷔 후 첫 안타를 2루타로 기록했습니다. 성공적인 메이저리그 신고식을 치렀습니다."
    },
    {
      "title": "[속보] 민주당, 임문영 AI전략위 부위원장 발탁...호남 전략공천",
      "originallink": "https://zdnet.co.kr/view/?no=20260506113339",
      "link": "https://n.news.naver.com/mnews/article/092/0002421463?sid=105",
      "description": "더불어민주당, 박지원 최고·임문영 국가인공지능전략위 부위원장 발탁. 임문영 부위원장, 광주 광산을 보궐선거 출마 가능성",
      "pubDate": "Wed, 06 May 2026 11:34:00 +0900",
      "formatted_date": "05월 06일, 11시 34분",
      "ai_summary": "더불어민주당이 임문영 국가인공지능전략위 부위원장을 발탁했습니다. 임 부위원장은 호남 지역 전략공천 및 보궐선거 출마 가능성이 제기됩니다."
    },
    {
      "title": "[속보] 코스피 7000선 돌파…급등에 매수 사이드카 발동 | ‘꿈의 7000’...",
      "originallink": "http://monthly.chosun.com/client/mdaily/daily_view.asp?idx=24302&Newsnumb=20260524302",
      "link": "http://monthly.chosun.com/client/mdaily/daily_view.asp?idx=24302&Newsnumb=20260524302",
      "description": "코스피가 삼성전자와 SK하이닉스의 강세로 ‘꿈의 7000’선을 넘겼다. 이같은 급등세에 약 한 달 만에 프로그램 매수호가 일시효력정지(매수 사이드카)가 발동됐다. 6일 한국거래소에 따르면 이날 오전 9시 6분... ",
      "pubDate": "Wed, 06 May 2026 11:32:00 +0900",
      "formatted_date": "05월 06일, 11시 32분",
      "ai_summary": "코스피가 삼성전자와 SK하이닉스 강세에 힘입어 7,000선을 돌파했습니다. 급등에 따라 매수 사이드카가 발동되었습니다."
    },
    {
      "title": "[속보] 공수처, 뇌물 수수 의혹 판사· 전주 지역 변호사 불구속 기소",
      "originallink": "http://www.jmbc.co.kr/news/view_breakingnews/64455",
      "link": "https://n.news.naver.com/mnews/article/659/0000043414?sid=102",
      "description": "전주지방법원 근무 당시 고교 동문 변호사가 제공한 금품을 받고 재판 관련 편의를 봐줬다는 혐의를 받는 부장판사가 재판에 넘겨졌습니다. 고위공직자범죄수사처는 특가법상 뇌물과 뇌물공여 등 혐의로 수도권 법원... ",
      "pubDate": "Wed, 06 May 2026 11:31:00 +0900",
      "formatted_date": "05월 06일, 11시 31분",
      "ai_summary": "공수처가 뇌물 수수 혐의를 받는 부장판사와 변호사를 불구속 기소했습니다. 판사는 재판 관련 편의를 봐주는 대가로 금품을 받은 혐의를 받습니다."
    }
  ],
  "pane2": {
    "산업부": [
      {
        "title": "산업부 &quot;올해 안 '물류센터 AI 표준모델' 구축... 중소 유통 AI 전환 가속...",
        "originallink": "https://www.pointe.co.kr/news/articleView.html?idxno=79162",
        "link": "https://www.pointe.co.kr/news/articleView.html?idxno=79162",
        "description": "산업부는 AI 도입을 통해 재고비용 절감과 배송시간 단축 등 생산성을 높이는 동시에, 물류 현장의 고위험... 산업부는 이번 간담회에서 논의된 'AI 자율운영 물류센터'의 조기 안착을 위해, 상품의 입고부터 출고까지의... ",
        "pubDate": "Wed, 06 May 2026 11:32:00 +0900",
        "formatted_date": "05월 06일, 11시 32분",
        "ai_summary": "산업부가 물류센터 내 재고 관리와 생산성 향상을 위해 AI 표준모델을 올해 안에 구축할 계획입니다. 중소 유통 현장의 AI 전환을 가속화합니다."
      },
      {
        "title": "산업부, 중소 유통물류에 AI 입힌다…표준모델 연내 구축",
        "originallink": "https://news.einfomax.co.kr/news/articleView.html?idxno=4413292",
        "link": "https://news.einfomax.co.kr/news/articleView.html?idxno=4413292",
        "description": "산업부는 6일 유통물류 업계 및 AI 전문가들과 간담회를 개최했다. 물류 혁신과 매장 지능화, 해외진출 지원 등 유통물류와 AI를 접목하는 프로젝트 현황을 살폈다. 산업부는 지난해 9월 '유통물류 AI 얼라이언스'를... ",
        "pubDate": "Wed, 06 May 2026 11:06:00 +0900",
        "formatted_date": "05월 06일, 11시 06분",
        "ai_summary": "산업부가 유통물류 업계와 AI 전문가 간담회를 열고 물류 혁신 및 지능화 방안을 논의했습니다. 중소 유통물류 분야에 AI 기술을 접목할 예정입니다."
      },
      {
        "title": "산업부, 유통물류 M.AX 본격화…연내 AI 표준모델 구축",
        "originallink": "https://www.ddaily.co.kr/page/view/2026050610593579399",
        "link": "https://n.news.naver.com/mnews/article/138/0002226930?sid=004",
        "description": "산업부는 5월 6일 유통물류 업계 및 유통분야 AI 전문가들과 간담회를 열고 ‘유통물류 M.AX(AI 전환)’ 프로젝트 현황 점검 및 ‘AI 자율운영 물류센터’ 추진 방안을 논의했다고 밝혔다. 이번 간담회에서 산업부는 AI... ",
        "pubDate": "Wed, 06 May 2026 11:04:00 +0900",
        "formatted_date": "05월 06일, 11시 04분",
        "ai_summary": "산업부가 유통물류 AI 전환(M.AX) 프로젝트를 본격화합니다. AI 자율운영 물류센터 구축을 위해 올해 내로 관련 표준모델을 마련할 계획입니다."
      },
      {
        "title": "&quot;유통물류센터에 AI 입힌다&quot;…산업부, 유통물류 M.AX 본격 추진",
        "originallink": "https://www.newsis.com/view/NISX20260506_0003617659",
        "link": "https://n.news.naver.com/mnews/article/003/0013927709?sid=101",
        "description": "산업부는 지난해 9월 유통물류 제조 인공지능 전환(M.AX) 추진을 위한 '유통물류 AI 얼라이언스'를 출범시키고... 산업부는 올해 중소형 물류센터에 적용 가능한 '물류센터 AI 표준모델'을 만들고... ",
        "pubDate": "Wed, 06 May 2026 11:00:00 +0900",
        "formatted_date": "05월 06일, 11시 00분",
        "ai_summary": "산업부가 중소형 물류센터의 경쟁력 강화를 위해 '물류센터 AI 표준모델'을 추진합니다. 지난해 출범한 유통물류 AI 얼라이언스와 협력할 예정입니다."
      },
      {
        "title": "농식품·산업부·농협, 농업용 필름 안정적 공급 나선다",
        "originallink": "https://www.yna.co.kr/view/AKR20260506074300030?input=1195m",
        "link": "https://n.news.naver.com/mnews/article/001/0016060297?sid=101",
        "description": "산업부에서 석유화학기업의 협조를 통해 농업용 필름 공급의 핵심이 되는 제조업체에 원료를 공급하면, 필름... 산업부는 진주원협의 원료 공급처인 한화솔루션과 협조해 이번 주에 농업용 필름 원료를 공급할 예정이다.... ",
        "pubDate": "Wed, 06 May 2026 11:00:00 +0900",
        "formatted_date": "05월 06일, 11시 00분",
        "ai_summary": "산업부와 농식품부, 농협이 농업용 필름의 안정적 공급을 위해 협력합니다. 석유화학기업과 연계해 제조업체에 원료를 원활히 공급할 방침입니다."
      },
      {
        "title": "김정관 산업부 장관, 캐나다·美 방문…파트너십 강화 나서",
        "originallink": "http://www.newscape.co.kr/news/articleView.html?idxno=122011",
        "link": "http://www.newscape.co.kr/news/articleView.html?idxno=122011",
        "description": "를 방문해 주요 인사들을 만나 캐나다·미국과의 경제·산업 분야 파트너십 강화 활동에 나선다. 김 장관은 5~6일 캐나다 오타와에서 멜라니 졸리 산업부 장관 및 팀 호지슨 에너지·천연자연부 장관을 만나 양국 간 산업 및... ",
        "pubDate": "Wed, 06 May 2026 09:36:00 +0900",
        "formatted_date": "05월 06일, 09시 36분",
        "ai_summary": "김정관 산업부 장관이 캐나다와 미국을 방문하여 경제 및 산업 분야의 파트너십 강화를 위한 활동을 펼친다."
      },
      {
        "title": "'한전이 원전수출 총괄' 법으로 못박는다…산업부 제정 검토",
        "originallink": "http://www.kookje.co.kr/news2011/asp/newsbody.asp?code=0200&key=20260505.99099000846",
        "link": "https://n.news.naver.com/mnews/article/658/0000142930?sid=101",
        "description": "원전 공기업의 수출 체계와 운영 방안을 법으로 규정해 글로벌 수주 시장에서 경쟁력을 강화하고 한전을 중심으로 국가적인 협상력을 결집한다는 게 산업부 계획이다. 다만 산업부 관계자는 “원전수출진흥법 입법 시기... ",
        "pubDate": "Tue, 05 May 2026 14:37:00 +0900",
        "formatted_date": "05월 05일, 14시 37분",
        "ai_summary": "산업부가 원전 수출 경쟁력 강화를 위해 한전을 총괄 기구로 하는 원전수출진흥법 제정을 검토하고 있다."
      },
      {
        "title": "산업부 &quot;한전 일원화 '원전수출진흥법' 확정된 바 없어&quot;",
        "originallink": "https://www.newsis.com/view/NISX20260505_0003617292",
        "link": "https://n.news.naver.com/mnews/article/003/0013926306?sid=101",
        "description": "산업부는 5일 &quot;원전수출진흥법 입법 시기 및 구체적 내용은 결정된 바 없다&quot;고 입장을 밝혔다. 최근 일부 언론은 산업부가 한전과 한국수력원자력으로 이원화된 수출 거버넌스를 한전으로 통합하는 '원전수출진흥법... ",
        "pubDate": "Tue, 05 May 2026 13:09:00 +0900",
        "formatted_date": "05월 05일, 13시 09분",
        "ai_summary": "산업부는 원전 수출 거버넌스를 한전으로 일원화하는 내용의 법안은 아직 구체적으로 결정된 바 없다고 밝혔다."
      }
    ],
    "KIAT": [
      {
        "title": "KIAT, 유럽 산학연과 바이오 공동R&amp;D 확대…국내 기업 진출 지원",
        "originallink": "https://news.tf.co.kr/read/economy/2319767.htm",
        "link": "https://n.news.naver.com/mnews/article/629/0000496858?sid=101",
        "description": "유레카 서밋 참가…한-스위스 기술협력 상담 추진 한국산업기술진흥원(KIAT)이 유럽 산학연과의 공동 연구개발(R&amp;D) 협력을 확대하며 국내 의료·바이오 기업의 해외 진출 지원에 속도를 내고 있다. KIAT는 6일(현지시각)... ",
        "pubDate": "Wed, 06 May 2026 11:01:00 +0900",
        "formatted_date": "05월 06일, 11시 01분",
        "ai_summary": "KIAT가 유럽 산학연과의 공동 R&D 협력을 확대하며 국내 바이오 기업의 해외 진출을 적극 지원하고 있다."
      },
      {
        "title": "KIAT, 韓바이오 기업 '국제공동 R&amp;D' 파트너 발굴 지원",
        "originallink": "https://www.newsis.com/view/NISX20260506_0003617867",
        "link": "https://n.news.naver.com/mnews/article/003/0013927707?sid=101",
        "description": "한국산업기술진흥원(KIAT)이 한-유럽 간 국제공동 연구개발(R&amp;D) 협력을 통해 국내 의료·바이오 기업의 첨단 기술 확보와 해외 시장 진출을 지원한다. KIAT는 6일(현지 시간) 스위스 바젤에서 열린 '유레카 글로벌... ",
        "pubDate": "Wed, 06 May 2026 11:00:00 +0900",
        "formatted_date": "05월 06일, 11시 00분",
        "ai_summary": "KIAT가 스위스에서 열린 유레카 서밋을 통해 국내 바이오 기업의 국제 공동 R&D 파트너 발굴을 지원했다."
      },
      {
        "title": "KIAT, K-바이오 유럽 진출·R&amp;D 지원",
        "originallink": "https://view.asiae.co.kr/article/2026050610124027163",
        "link": "https://n.news.naver.com/mnews/article/277/0005758791?sid=101",
        "description": "KIAT)이 국내 의료·바이오 기업의 유럽 시장 진출과 첨단 기술 확보를 위한 국제공동 연구개발(R&amp;D) 지원에 나섰다. 유럽 연구기관 및 기업과의 협력을 통해 글로벌 바이오 생태계 진입을 확대하겠다는 구상이다. KIAT는... ",
        "pubDate": "Wed, 06 May 2026 10:12:00 +0900",
        "formatted_date": "05월 06일, 10시 12분",
        "ai_summary": "KIAT가 국내 바이오 기업의 유럽 시장 진출과 첨단 기술 확보를 위한 국제 공동 연구개발 지원에 나섰다."
      },
      {
        "title": "전윤종 KIAT 원장 &quot;내년 베트남에 광물 기술협력센터 설립&quot;",
        "originallink": "https://view.asiae.co.kr/article/2026042914283869102",
        "link": "https://n.news.naver.com/mnews/article/277/0005756595?sid=101",
        "description": "한국산업기술진흥원(KIAT·원장 전윤종)이 내년 베트남 하노이에 핵심 광물 공급망 기술협력센터(이하 센터)... KIAT는 센터가 마련되면 ▲광물을 다룰 전문 인력에 대한 교육과정을 현지 개설하고 ▲광물 고부가가치화에... ",
        "pubDate": "Wed, 29 Apr 2026 14:28:00 +0900",
        "formatted_date": "04월 29일, 14시 28분",
        "ai_summary": "전윤종 KIAT 원장이 내년 베트남 하노이에 핵심 광물 공급망 기술협력센터를 설립하겠다고 밝혔다."
      },
      {
        "title": "베트남에 핵심광물 활용 기술 노하우 전수…KIAT, ‘핵심광물 전략 포럼...",
        "originallink": "https://www.busan.com/view/busan/view.php?code=2026042422473224547",
        "link": "https://n.news.naver.com/mnews/article/082/0001377742?sid=101",
        "description": "한국산업기술진흥원(KIAT, 원장 전윤종)은 24일(현지시간) 베트남 하노이 인터컨티넨탈 호텔에서 ‘한... 이날 포럼에는 KIAT 및 베트남 산업무역부(MOIT)를 비롯해 사업 수행기관, 양국의 광업 기업 관계자 80여 명이 참석해... ",
        "pubDate": "Fri, 24 Apr 2026 22:51:00 +0900",
        "formatted_date": "04월 24일, 22시 51분",
        "ai_summary": "KIAT가 베트남 하노이에서 전략 포럼을 열고 핵심 광물 활용 기술 노하우 전수 및 협력 방안을 논의했다."
      },
      {
        "title": "부천대 학교기업 제펫스튜디오 교육부·KIAT 주관 '4단계 학교기업지원...",
        "originallink": "https://www.kyosu.net/news/articleView.html?idxno=204777",
        "link": "https://www.kyosu.net/news/articleView.html?idxno=204777",
        "description": "부천대학교(총장 한정석) 학교기업 제펫스튜디오는 지난 4월 13일, 교육부와 한국산업기술진흥원(KIAT)이 주관하는 '4단계 학교기업 지원사업' 계속지원 대상에 선정되었다고 밝혔다. 이번 선정은 제펫스튜디오가 추진해 온... ",
        "pubDate": "Fri, 24 Apr 2026 20:28:00 +0900",
        "formatted_date": "04월 24일, 20시 28분",
        "ai_summary": "부천대학교 학교기업 제펫스튜디오가 교육부와 KIAT가 주관하는 4단계 학교기업 지원사업 대상자로 선정됐다."
      },
      {
        "title": "전윤종 신임 KIAT 원장 “산업 AI 혁신, 5극3특 균형 발전 기술 혁신 차...",
        "originallink": "https://www.viva100.com/article/20260421500954",
        "link": "https://www.viva100.com/article/20260421500954",
        "description": "전윤종 6대 한국산업기술진흥원(KIAT) 원장이 산업의 인공지능(AI) 혁신과 5극3특으로 대표되는 지역 균형 발전 정책을 기술 혁신 차원에서 뒷받침하겠다는 취임 의지를 강조했다. 전윤종 신임 산업기술진흥원장은 21일... ",
        "pubDate": "Tue, 21 Apr 2026 16:06:00 +0900",
        "formatted_date": "04월 21일, 16시 06분",
        "ai_summary": "전윤종 신임 KIAT 원장이 산업 AI 혁신과 기술 중심의 지역 균형 발전을 뒷받침하겠다는 포부를 밝혔다."
      }
    ],
    "기후부": [
      {
        "title": "기후부, 전국 공영동물원 협의체 구성",
        "originallink": "http://www.ikld.kr/news/articleView.html?idxno=334033",
        "link": "http://www.ikld.kr/news/articleView.html?idxno=334033",
        "description": "회의에는 이채은 기후부 자연보전국장을 비롯해 유역(지방)환경청, 국립생태원, 한국동물원수족관협회, 전국 공영동물원 관계자 등이 참석, 회의를 갖는다. 이채은 국장은 &quot;이번 협의체 출범을 계기로 공영동물원 간 상시... ",
        "pubDate": "Wed, 06 May 2026 10:22:00 +0900",
        "formatted_date": "05월 06일, 10시 22분",
        "ai_summary": "기후부가 전국 공영동물원 간의 상시 협력 체계 구축을 위해 협의체를 구성함. 공영동물원 관계자 등이 참여해 안전 관리 및 운영을 논의함."
      },
      {
        "title": "[산업부·기후부 장차관 일정(2026년 5월 6일)]",
        "originallink": "http://www.e-platform.net/news/articleView.html?idxno=102010",
        "link": "http://www.e-platform.net/news/articleView.html?idxno=102010",
        "description": "◆ 산업통상부 ▲ 장관: 국외 출장 (캐나다, 미국 / 5.5~5.8) ▲ 차관: 10:00 국무회의 ◆ 기후부 ▲ 장관: 10:00 국무회의 (서울) 14:00 법사위 (서울) 17:00 재생열 적용 정책 현장 방문 (서울)",
        "pubDate": "Wed, 06 May 2026 08:36:00 +0900",
        "formatted_date": "05월 06일, 08시 36분",
        "ai_summary": "2026년 5월 6일 산업부와 기후부 장차관의 국무회의, 국외 출장 및 정책 현장 방문 등의 주요 일정을 안내함."
      },
      {
        "title": "기후부, 폐플라스틱 열분해 활성화 등 순환경제분야 규제특례 과제 12건...",
        "originallink": "http://www.e-platform.net/news/articleView.html?idxno=102008",
        "link": "http://www.e-platform.net/news/articleView.html?idxno=102008",
        "description": "기후부가 순환경제분야 규제특례 과제 12건을 승인했다. 승인된 규제특례 과제들은 지정된 기간, 장소, 규모에서 새로운 기술과 서비스 실증이 가능하다. 기후에너지환경부는 지난달 30일 서울스퀘어(서울 중구 소재)에서... ",
        "pubDate": "Tue, 05 May 2026 22:04:00 +0900",
        "formatted_date": "05월 05일, 22시 04분",
        "ai_summary": "기후부가 폐플라스틱 열분해 등 순환경제 분야의 신기술·서비스 실증을 위한 규제특례 과제 12건을 승인함."
      },
      {
        "title": "VPP부터 마이크로그리드까지…기후부 '지능형전력망' 전환 가속",
        "originallink": "https://www.asiatoday.co.kr/kn/view.php?key=20260505010000695",
        "link": "https://www.asiatoday.co.kr/kn/view.php?key=20260505010000695",
        "description": "기후부 올해 '지능형전력망 시행계획' 공고 제3차 지능형전력망 기본계획의 세부 실행안 계통포화지역... 이를 위해 주택법 등 관련 법 개정이 필요한 만큼 기후부는 연내 개정 작업에 나설 계획이다. 이와 함께... ",
        "pubDate": "Tue, 05 May 2026 18:02:00 +0900",
        "formatted_date": "05월 05일, 18시 02분",
        "ai_summary": "기후부가 제3차 지능형전력망 기본계획의 일환으로 VPP와 마이크로그리드 전환을 가속화함. 이를 위해 연내 관련 법 개정을 추진할 예정임."
      },
      {
        "title": "기후부, 생활화학제품 표시방식 등 '규제특례' 12건 승인",
        "originallink": "http://www.metroseoul.co.kr/article/20260505500100",
        "link": "http://www.metroseoul.co.kr/article/20260505500100",
        "description": "세종 기후부 청사 /뉴시스 기후에너지환경부가 12건의 폐기물 처리 과제에 대해 '순환경제 규제특례'(샌드박스)를 부여했다. 폐합성수지의 열분해 재활용 활성화, 생활화학제품 표시방식 개선 등이다. 기후부는 최근 개최한... ",
        "pubDate": "Tue, 05 May 2026 13:44:00 +0900",
        "formatted_date": "05월 05일, 13시 44분",
        "ai_summary": "기후부가 폐기물 처리 과제 12건에 대해 순환경제 규제특례를 부여함. 폐합성수지 열분해 재활용과 생활화학제품 표시방식 개선 등이 포함됨."
      },
      {
        "title": "늑대 늑구 탈출 재발 막는다…기후부, 공영동물원 협의체 출범",
        "originallink": "https://www.ajunews.com/view/20260505121702969",
        "link": "https://www.ajunews.com/view/20260505121702969",
        "description": "이날 출범 회의에는 이채은 기후부 자연보전국장을 비롯해 유역(지방)환경청, 국립생태원, 한국동물원수족관협회, 전국 공영동물원 관계자 등이 참석한다. 기후부는 이번 협의체 출범을 계기로 공영동물원 간 상시 협력... ",
        "pubDate": "Tue, 05 May 2026 12:30:00 +0900",
        "formatted_date": "05월 05일, 12시 30분",
        "ai_summary": "동물 탈출 사고 재발 방지를 위해 기후부가 공영동물원 협의체를 출범함. 동물원 간 협력을 강화해 안전과 복지를 제고할 계획임."
      },
      {
        "title": "기후부, 폐플라스틱 열분해 등 '순환경제 샌드박스' 12건 승인",
        "originallink": "https://www.ajunews.com/view/20260505115404935",
        "link": "https://www.ajunews.com/view/20260505115404935",
        "description": "기후부는 지난달 30일 서울스퀘어에서 '순환경제 신기술·서비스 심의위원회'를 개최하고 이같은 내용의... 김고응 기후부 자원순환국장은 &quot;승인된 과제를 비롯해 플라스틱의 고품질 순환 이용과 감량을 위해 다각적으로... ",
        "pubDate": "Tue, 05 May 2026 12:02:00 +0900",
        "formatted_date": "05월 05일, 12시 02분",
        "ai_summary": "기후부가 순환경제 신기술·서비스 심의위원회를 열고 폐플라스틱 열분해 등 12건의 규제 샌드박스 과제를 승인함. 플라스틱 순환 이용 활성화를 목표로 함."
      },
      {
        "title": "“폐합성수지 열분해 길 터준다”…기후부, 순환자원 기준 손질·샌드박...",
        "originallink": "https://www.etnews.com/20260505000050",
        "link": "https://n.news.naver.com/mnews/article/030/0003424260?sid=101",
        "description": "김고응 기후부 자원순환국장은 “플라스틱의 고품질 순환이용·감량 다각적으로 지원하고 사회 전분야에 순환경제가 확산될 수 있도록 산업계와 재활용 기술 현장 적용성을 높이겠다”고 밝혔다.",
        "pubDate": "Tue, 05 May 2026 12:01:00 +0900",
        "formatted_date": "05월 05일, 12시 01분",
        "ai_summary": "기후부가 폐합성수지 열분해 활성화를 위해 순환자원 기준을 손질함. 산업계의 재활용 기술 적용성을 높여 순환경제를 확산할 계획임."
      },
      {
        "title": "기후부, 순환경제 샌드박스 과제 12건 승인…폐합성수지 열분해 활성화",
        "originallink": "https://www.newsis.com/view/NISX20260505_0003617186",
        "link": "https://n.news.naver.com/mnews/article/003/0013926094?sid=101",
        "description": "기후부는 지난달 30일 서울 중구 서울스퀘어에서 '순환경제 신기술·서비스 심의위원회'를 개최한 결과를 5일... 김고응 기후부 자원순환국장은 &quot;이번에 승인한 과제를 비롯해 플라스틱의 고품질 순환이용 및 감량을 위해... ",
        "pubDate": "Tue, 05 May 2026 12:00:00 +0900",
        "formatted_date": "05월 05일, 12시 00분",
        "ai_summary": "기후부가 순환경제 샌드박스를 통해 폐합성수지 열분해 등 12개 과제를 승인함. 플라스틱 감량 및 고품질 순환 이용을 지원함."
      },
      {
        "title": "기후부, ‘공영동물원 협의체’ 출범···‘늑구 탈출’ 재발 막을까",
        "originallink": "https://www.khan.co.kr/article/202605051200001",
        "link": "https://n.news.naver.com/mnews/article/032/0003443877?sid=102",
        "description": "지난달 22일 기후부는 2028년 12월이었던 기존 전환 시한을 1년 앞당겨 2027년 12월까지 전체 동물원의 90% 이상을... 이채은 기후부 자연보전국장은 “공영동물원이 허가 요건을 내실 있게 갖춰 안전 관리와 동물 복지 수준을... ",
        "pubDate": "Tue, 05 May 2026 12:00:00 +0900",
        "formatted_date": "05월 05일, 12시 00분",
        "ai_summary": "기후부가 공영동물원 협의체를 출범해 동물 탈출 재발 방지 및 관리 강화에 나섬. 2027년까지 동물원의 90% 이상을 허가제로 전환할 계획임."
      }
    ],
    "산업혁신기반구축": []
  },
  "pane3": {
    "호르무즈": [
      {
        "title": "HMM “호르무즈 정박 나무호, 오늘 오후 예인 시작”",
        "originallink": "https://news.kbs.co.kr/news/pc/view/view.do?ncd=8553949&ref=A",
        "link": "https://n.news.naver.com/mnews/article/056/0012175653?sid=101",
        "description": "호르무즈 해협 안쪽에 정박 중 폭발·화재 사고가 난 한국 선박 ‘HMM 나무호’에 대한 예인 작업이 오늘(6일) 오후 시작됩니다. HMM 관계자는 “나무호의 예인과 수리에 대한 계약을 모두 마쳤다”면서 “한국 시각으로... ",
        "pubDate": "Wed, 06 May 2026 11:50:00 +0900",
        "formatted_date": "05월 06일, 11시 50분",
        "ai_summary": "호르무즈 해협에서 화재가 발생한 한국 선박 'HMM 나무호'의 예인 작업이 6일 오후 시작됩니다. HMM 측은 예인 및 수리 계약을 모두 마쳤다고 밝혔습니다."
      },
      {
        "title": "美, 유엔 통해 이란 호르무즈 개방 압박…안보리 결의 재추진",
        "originallink": "https://www.nocutnews.co.kr/news/6512721?utm_source=naver&utm_medium=article&utm_campaign=20260506114852",
        "link": "https://n.news.naver.com/mnews/article/079/0004143849?sid=104",
        "description": "이란의 호르무즈 해협 개방을 압박하고 나섰다. 마코 루비오 미 국무부 장관은 5일(현지시간) 바레인, 사우디아라비아, 아랍에미리트(UAE), 쿠웨이트, 카타르 등과 공동으로 성명을 내고 호르무즈 해협의 안전 확보를... ",
        "pubDate": "Wed, 06 May 2026 11:49:00 +0900",
        "formatted_date": "05월 06일, 11시 49분",
        "ai_summary": "미국이 이란의 호르무즈 해협 개방을 압박하기 위해 안보리 결의를 재추진합니다. 미 국무장관은 주요 중동 국가들과 공동 성명을 내고 해협의 안전 확보를 촉구했습니다."
      },
      {
        "title": "호르무즈 봉쇄 후 세 번째 한국 유조선 홍해 통과",
        "originallink": "https://www.dt.co.kr/article/12060986?ref=naver",
        "link": "https://n.news.naver.com/mnews/article/029/0003025215?sid=101",
        "description": "호르무즈 해협 봉쇄 이후 각국 선박들이 우회로운 홍해로 원유를 운반하는 가운데, 한국 선박이 3번째로... 많은 중동 국가들은 호르무즈 해협을 통해 원유를 운반하고 있지만, 사우디아라비아는 호르무즈 해협의 반대편인... ",
        "pubDate": "Wed, 06 May 2026 11:49:00 +0900",
        "formatted_date": "05월 06일, 11시 49분",
        "ai_summary": "호르무즈 해협 봉쇄로 인해 한국 선박들이 우회로인 홍해를 통해 원유를 운송하고 있습니다. 이번이 벌써 세 번째 홍해 통과 사례입니다."
      },
      {
        "title": "호르무즈 화재 선박서 ‘선체에 구멍난 흔적’ 없어…정밀조사 필요",
        "originallink": "https://www.dt.co.kr/article/12060985?ref=naver",
        "link": "https://n.news.naver.com/mnews/article/029/0003025214?sid=101",
        "description": "호르무즈 해협에서 정박 중 폭발·화재 사고가 발생한 중소형 벌크 화물선 HMM 나무호에 군사적 공격을 의심할 수 있는 파공의 흔적이 발견되지 않은 것으로 알려졌다. 피격설보다는 내부 폭발에 무게가 실리는 정황으로... ",
        "pubDate": "Wed, 06 May 2026 11:48:00 +0900",
        "formatted_date": "05월 06일, 11시 48분",
        "ai_summary": "사고 선박인 HMM 나무호에서 외부 공격을 암시하는 파공 흔적이 발견되지 않았습니다. 이에 따라 피격보다는 내부 폭발 사고 가능성에 무게가 실리고 있습니다."
      },
      {
        "title": "국무회의서 호르무즈 동향 보고받은 李대통령…구체적 언급 자제",
        "originallink": "https://www.yna.co.kr/view/AKR20260506086100001?input=1195m",
        "link": "https://n.news.naver.com/mnews/article/001/0016060569?sid=100",
        "description": "장관으로부터 호르무즈 해협에서 벌어진 한국 선박의 화재 사고 및 중동전쟁 진행 상황에 대한 보고를... 실제로 청와대는 전날 &quot;미국 측의 호르무즈 해협 관련 제안에 대해 한반도 대비 태세와 국내법 절차 등을 감안해... ",
        "pubDate": "Wed, 06 May 2026 11:46:00 +0900",
        "formatted_date": "05월 06일, 11시 46분",
        "ai_summary": "이 대통령이 국무회의에서 호르무즈 선박 사고와 중동 정세에 대해 보고받았습니다. 청와대는 미국 측 제안과 관련해 신중한 태도를 유지하고 있습니다."
      },
      {
        "title": "트럼프 “한국 화물선, 호르무즈서 단독 운항 중 공격”…정부는 원인 ...",
        "originallink": "https://news.knn.co.kr/news/article_sns/1261",
        "link": "https://news.knn.co.kr/news/article_sns/1261",
        "description": "도널드 트럼프 미국 대통령이 호르무즈 해협에서 화재가 발생한 한국 화물선과 관련해 이란의 공격을 받았다고 주장했습니다. 트럼프 대통령은 5일(현지시간) 백악관 행사에서 한국이 호르무즈 해협을 통해 석유의 43%를... ",
        "pubDate": "Wed, 06 May 2026 11:46:00 +0900",
        "formatted_date": "05월 06일, 11시 46분",
        "ai_summary": "트럼프 미국 대통령이 호르무즈 해협 사고 선박이 이란의 공격을 받았다고 주장했습니다. 그러나 정확한 사고 원인에 대해서는 우리 정부 조사가 진행 중입니다."
      },
      {
        "title": "소방청, 호르무즈 선박 화재·폭발 관련 전문 조사관 2명 파견 예정",
        "originallink": "https://news.kbs.co.kr/news/pc/view/view.do?ncd=8553928&ref=A",
        "link": "https://n.news.naver.com/mnews/article/056/0012175649?sid=102",
        "description": "호르무즈 해협에서 발생한 한국 선박 폭발·화재 사고와 관련해 소방청이 전문 인력 2명을 현장에... 앞서 한국 시간으로 지난 4일 오후 8시 40분쯤 호르무즈 해협 내 아랍에미리트연합(UAE) 인근 해역에 정박 중이던 한국... ",
        "pubDate": "Wed, 06 May 2026 11:44:00 +0900",
        "formatted_date": "05월 06일, 11시 44분",
        "ai_summary": "소방청이 호르무즈 해협 선박 폭발 및 화재 사고의 원인을 규명하기 위해 전문 조사관 2명을 현장에 파견할 예정입니다."
      },
      {
        "title": "호르무즈 봉쇄 후 세번째 韓 유조선 홍해 통과해",
        "originallink": "https://www.chosun.com/economy/economy_general/2026/05/06/3AG7P2P5HJDP3IT2ZLPH3XSAZE/?utm_source=naver&utm_medium=referral&utm_campaign=naver-news",
        "link": "https://n.news.naver.com/mnews/article/023/0003974865?sid=101",
        "description": "호르무즈 해협 봉쇄 이후 세 번째로 한국 선박이 우회로인 홍해를 통과해 국내로 원유를 운송하게 됐다.... 호르무즈 해협이 봉쇄되면서 홍해를 통해 국내로 원유를 운송하는 사례가 이어지고 있지만, 홍해도 예멘 후티... ",
        "pubDate": "Wed, 06 May 2026 11:43:00 +0900",
        "formatted_date": "05월 06일, 11시 43분",
        "ai_summary": "호르무즈 해협 봉쇄에 대응해 세 번째 한국 유조선이 홍해를 통과했습니다. 다만 홍해 지역의 안보 불안은 여전히 해결해야 할 과제로 남아있습니다."
      },
      {
        "title": "HMM, '호르무즈 폭발' 선박 위한 예인선 확보…&quot;원인 규명 작업 돌입&quot;",
        "originallink": "https://www.newsis.com/view/NISX20260506_0003618365",
        "link": "https://n.news.naver.com/mnews/article/003/0013927931?sid=101",
        "description": "HMM이 호르무즈 해협 인근에서 화재가 발생한 선박을 이동하기 위한 예인선을 6일 확보했다. 이르면 이날 오후 예인을 시작할 예정이다. 선박을 두바이로 옮겨 수리에 착수하는 것이다. HMM 관계자는 이날 &quot;이르면 7일 밤... ",
        "pubDate": "Wed, 06 May 2026 11:43:00 +0900",
        "formatted_date": "05월 06일, 11시 43분",
        "ai_summary": "HMM이 사고 선박을 두바이로 옮기기 위한 예인선을 확보했습니다. 선박을 안전하게 이동시킨 뒤 본격적인 사고 원인 조사와 수리에 착수할 계획입니다."
      },
      {
        "title": "호르무즈 HMM 선박 사고에 민주당 &quot;국민의 생명과 안전은 국가의 최우선...",
        "originallink": "https://www.ngonews.kr/news/articleView.html?idxno=229466",
        "link": "https://www.ngonews.kr/news/articleView.html?idxno=229466",
        "description": "지난 4일 호르무즈 해협 내측 아랍에미리트(UAE) 인근 해역에 정박 중이던 우리 선사 HMM 나무호에서폭발과... (4일)에 호르무즈 해협에 있던 우리 선사 HMM 운영 선박에서 폭발 화재 사고가 발생했다. 선박에는 우리 선원 6명을... ",
        "pubDate": "Wed, 06 May 2026 11:42:00 +0900",
        "formatted_date": "05월 06일, 11시 42분",
        "ai_summary": "더불어민주당은 호르무즈 해협 선박 사고와 관련해 국민의 생명과 안전을 최우선으로 보호할 것을 정부에 강력히 촉구했습니다."
      }
    ],
    "트럼프": [
      {
        "title": "[이슈] 트럼프 &quot;이란과 최종합의 향한 큰 진전…프로젝트 프리덤 중단&quot;...",
        "originallink": "https://www.polinews.co.kr/news/articleView.html?idxno=730296",
        "link": "https://www.polinews.co.kr/news/articleView.html?idxno=730296",
        "description": "도널드 트럼프 미국 대통령이 5일(이하 현지시간) 이란과의 협상에서 상당한 진전이 이뤄졌다면서 호르무즈... 보이자 트럼프 대통령이 이를 철회한 것이라는 해석이다. 같은 날 마코 루비오 미국 국무장관이 이번 대이란... ",
        "pubDate": "Wed, 06 May 2026 11:52:00 +0900",
        "formatted_date": "05월 06일, 11시 52분",
        "ai_summary": "트럼프 대통령이 이란과의 협상에 큰 진전이 있었다며 '프로젝트 프리덤' 중단을 발표했습니다. 대이란 해상 봉쇄 정책은 계속 유지될 방침입니다."
      },
      {
        "title": "트럼프 “한국 화물선, 호르무즈서 단독 운항 중 공격”…정부는 원인 ...",
        "originallink": "https://news.knn.co.kr/news/article_sns/1261",
        "link": "https://news.knn.co.kr/news/article_sns/1261",
        "description": "도널드 트럼프 미국 대통령이 호르무즈 해협에서 화재가 발생한 한국 화물선과 관련해 이란의 공격을 받았다고 주장했습니다. 트럼프 대통령은 5일(현지시간) 백악관 행사에서 한국이 호르무즈 해협을 통해 석유의 43%를... ",
        "pubDate": "Wed, 06 May 2026 11:46:00 +0900",
        "formatted_date": "05월 06일, 11시 46분",
        "ai_summary": "트럼프 대통령은 호르무즈 해협에서 발생한 한국 화물선 화재를 이란의 공격으로 규정했습니다. 우리 정부는 정확한 사고 원인을 파악 중입니다."
      },
      {
        "title": "'나무호' 폭발 사고 논란…트럼프 &quot;단독 행동 피격&quot; vs HMM &quot;정박 상태, ...",
        "originallink": "https://www.ddaily.co.kr/page/view/2026050611163622601",
        "link": "https://n.news.naver.com/mnews/article/138/0002226940?sid=101",
        "description": "도널드 트럼프 미국 대통령이 호르무즈 해협에 갇힌 각국 선박들이 무사히 빠져나올 수 있도록 하기 위한... 이와 관련해 트럼프 대통령은 &quot;한국 선박이 단독 행동을 하다가 공격을 당한 것&quot;이라 주장하며 논란을... ",
        "pubDate": "Wed, 06 May 2026 11:46:00 +0900",
        "formatted_date": "05월 06일, 11시 46분",
        "ai_summary": "호르무즈 해협에서 발생한 '나무호' 폭발 사고에 대해 트럼프는 한국 선박의 단독 행동으로 인한 피격이라 주장했습니다. 반면 HMM 측은 정박 중 사고였다고 반박했습니다."
      },
      {
        "title": "운동 많이 한다더니 하루 딱 ‘1분’?…트럼프 농담에 백악관 ‘빵’ 터...",
        "originallink": "https://www.sedaily.com/article/20040694?ref=naver",
        "link": "https://n.news.naver.com/mnews/article/011/0004617849?sid=104",
        "description": "도널드 트럼프 미국 대통령이 ‘대통령 체력검사’ 제도 부활을 선언하는 자리에서 자신의 운동 습관을... 5일(현지시간) 미국 정치전문매체 더힐 등에 따르면 트럼프 대통령은 백악관에서 ‘대통령 체력검사(Presidential... ",
        "pubDate": "Wed, 06 May 2026 11:46:00 +0900",
        "formatted_date": "05월 06일, 11시 46분",
        "ai_summary": "트럼프 대통령이 '대통령 체력검사' 부활 행사에서 자신의 운동 습관을 농담 섞어 언급하며 청중들의 웃음을 자아냈습니다."
      },
      {
        "title": "트럼프 “해방 프로젝트 잠시 중단…이란과 합의 큰 진전”",
        "originallink": "https://biz.heraldcorp.com/article/10731949?ref=naver",
        "link": "https://n.news.naver.com/mnews/article/016/0002639565?sid=104",
        "description": "시행 하루만에…협상국면 급전환 대이란 해상 봉쇄는 전면적 유지 “韓선박 단독행동하다 공격 당해” 도널드 트럼프 대통령이 5일(현지시간) 포고령 서명식에서 제스처를 취하고 있다. [AFP] 도널드 트럼프 미국 대통령은... ",
        "pubDate": "Wed, 06 May 2026 11:44:00 +0900",
        "formatted_date": "05월 06일, 11시 44분",
        "ai_summary": "트럼프 대통령이 이란과의 합의 진전을 이유로 해방 프로젝트를 중단했습니다. 또한 호르무즈 해협 내 한국 선박 공격 사건을 언급했습니다."
      },
      {
        "title": "또 입장 바꾼 트럼프… &quot;韓, 프로젝트 프리덤 참여해야&quot;→&quot;작전 임시 중...",
        "originallink": "https://www.thepublic.kr/news/articleView.html?idxno=303388",
        "link": "https://www.thepublic.kr/news/articleView.html?idxno=303388",
        "description": "도널드 트럼프 미국 대통령이 호르무즈 해협에서 발생한 한국 화물선 HMM 나무호(이하 나무호)의 폭발·화재... 트럼프 대통령은 5일(현지 시각) 소셜 미디어 트루스소셜을 통해 프로젝트 프리덤을 잠시 중단하기로 했다고... ",
        "pubDate": "Wed, 06 May 2026 11:44:00 +0900",
        "formatted_date": "05월 06일, 11시 44분",
        "ai_summary": "트럼프 대통령이 '프로젝트 프리덤'에 대한 입장을 번복하며 잠시 중단하겠다고 밝혔습니다. 이는 호르무즈 해협 내 한국 선박 사고 직후 나온 조치입니다."
      },
      {
        "title": "트럼프의 '교황 비판' 이어져 '루비오의 바티칸 방문 차질'",
        "originallink": "http://www.newstown.co.kr/news/articleView.html?idxno=702592",
        "link": "http://www.newstown.co.kr/news/articleView.html?idxno=702592",
        "description": "미국인 출신 최초의 레오 14세(Leo XIV) 교황과 도널드 트럼프 미국 대통령 도널드 J. 트럼프 미국 대통령이 교황 레오 14세(Pope Leo XIV)를 다시 한번 비난하면서, 이번 주 마르코 루비오 국무장관의 바티칸 방문에 차질이 생길... ",
        "pubDate": "Wed, 06 May 2026 11:39:00 +0900",
        "formatted_date": "05월 06일, 11시 39분",
        "ai_summary": "트럼프 대통령이 레오 14세 교황을 반복해서 비난함에 따라 마르코 루비오 국무장관의 바티칸 방문 일정에 차질이 빚어지고 있습니다."
      },
      {
        "title": "트럼프 &quot;협상 진전&quot;에도…이란 대통령 &quot;누구도 항복 강요 못해&quot;",
        "originallink": "https://www.news1.kr/world/usa-canada/6158003",
        "link": "https://n.news.naver.com/mnews/article/421/0008928450?sid=104",
        "description": "통항을 보장하기 위한 작전 '프로젝트 프리덤'(Project Freedom)을 개시했다. 이후 도널드 트럼프 미국 대통령은 이날 이란과의 협상이 진전되고 있다며 프로젝트 프리덤을 단기간 중단하기로 이란과 합의했다고 주장했다.",
        "pubDate": "Wed, 06 May 2026 11:39:00 +0900",
        "formatted_date": "05월 06일, 11시 39분",
        "ai_summary": "트럼프 대통령은 협상 진전을 이유로 프로젝트 프리덤 중단을 발표했으나, 이란 대통령은 항복 강요를 거부하며 강경한 입장을 보였습니다."
      },
      {
        "title": "S&amp;P500 선물, 트럼프 '해방 프로젝트' 중단에 상승",
        "originallink": "https://news.einfomax.co.kr/news/articleView.html?idxno=4413309",
        "link": "https://news.einfomax.co.kr/news/articleView.html?idxno=4413309",
        "description": "6일 오전 아시아 시장에서 미국 주가지수 선물은 도널드 트럼프 미국 대통령의 호르무즈 해협에 갇혀... 도널드 트럼프 미국 대통령은 트루스소셜에 올린 게시글에서 &quot;우리는 상호 합의하에 봉쇄는 계속... ",
        "pubDate": "Wed, 06 May 2026 11:36:00 +0900",
        "formatted_date": "05월 06일, 11시 36분",
        "ai_summary": "트럼프 대통령의 '프로젝트 프리덤' 중단 발표 소식에 아시아 시장에서 미국 S&P500 주가지수 선물이 상승세를 보였습니다."
      },
      {
        "title": "트럼프 행정부 평등고용위, NYT 제소…&quot;백인 남성 차별&quot;",
        "originallink": "http://www.edaily.co.kr/news/newspath.asp?newsid=04778966645446296",
        "link": "https://n.news.naver.com/mnews/article/018/0006273993?sid=104",
        "description": "도널드 트럼프 행정부가 추진 중인 다양성·형평성·포용성(DEI) 배제 정책이 미국 대표 언론사로 확산하는... 이번 소송은 NYT가 지난달 말 자체 보도에서 “EEOC가 트럼프 대통령 취임 이후 그의 어젠다에 부합하는... ",
        "pubDate": "Wed, 06 May 2026 11:35:00 +0900",
        "formatted_date": "05월 06일, 11시 35분",
        "ai_summary": "트럼프 행정부의 평등고용위가 뉴욕타임스를 백인 남성 차별 혐의로 제소했습니다. 이는 트럼프 행정부의 DEI 배제 정책의 일환입니다."
      }
    ],
    "유가": [
      {
        "title": "영동군, 고유가 지원금 82% 지급…641명 겨냥 '찾아가는 신청' 가동",
        "originallink": "https://www.inews365.com/news/article.html?no=918103",
        "link": "https://www.inews365.com/news/article.html?no=918103",
        "description": "영동군이 고유가 피해지원금 미신청자를 줄이기 위해 '찾아가는 신청 서비스'를 전면 가동했다. 영동군에 따르면 1차 고유가 피해지원금 지급률은 5일 기준 82%다. 전체 대상자 3천541명 중 2천900명에게 지급이 완료됐다.... ",
        "pubDate": "Wed, 06 May 2026 11:52:00 +0900",
        "formatted_date": "05월 06일, 11시 52분",
        "ai_summary": "영동군이 고유가 피해지원금 미신청자를 위해 찾아가는 신청 서비스를 가동함. 현재 1차 지급률은 82%를 기록 중임."
      },
      {
        "title": "서산시, 고유가 피해 지원금 사용처 확대 안내",
        "originallink": "https://www.ccdailynews.com/news/articleView.html?idxno=2414296",
        "link": "https://www.ccdailynews.com/news/articleView.html?idxno=2414296",
        "description": "▲ 고유가 피해 지원금 주유소 사용처 확대 홍보물. 충남 서산시는 고유가 피해 지원금의 사용처가 지역내 모든 주유소·LPG 충전소로 확대됐다고 밝혔다. 고유가 피해 지원금은 소상공인 보호를 위해 연 매출 30억원... ",
        "pubDate": "Wed, 06 May 2026 11:50:00 +0900",
        "formatted_date": "05월 06일, 11시 50분",
        "ai_summary": "서산시가 고유가 피해 지원금의 사용처를 지역 내 모든 주유소와 LPG 충전소로 확대함. 소상공인 보호를 위한 조치임."
      },
      {
        "title": "미국 &quot;공격 중단, 휴전 계속&quot; 협상 기대에 국제유가 하락",
        "originallink": "https://www.koreareport.co.kr/news/articleView.html?idxno=50289",
        "link": "https://www.koreareport.co.kr/news/articleView.html?idxno=50289",
        "description": "호르무즈 해협에서 유조선과 LNG운반선은 여전히 빠져 나오지 못하지만 휴전 상태가 계속된다는 안도감에 국제유가는 하락했다. 트레이딩이코노믹스에 따르면 6일(한국시간) 오전 미국 텍사스유는 100.8달러, 국제거래... ",
        "pubDate": "Wed, 06 May 2026 11:48:00 +0900",
        "formatted_date": "05월 06일, 11시 48분",
        "ai_summary": "중동 휴전 협상에 대한 기대감이 커지면서 에너지 시장의 불안이 완화됨에 따라 국제 유가가 하락함."
      },
      {
        "title": "모내기에 기름 필수인데...고유가에 농가 '걱정'",
        "originallink": "https://www.ytn.co.kr/_ln/0115_202605061147032975",
        "link": "https://n.news.naver.com/mnews/article/052/0002349303?sid=102",
        "description": "이에 정부는 농가의 유류비 부담을 덜기 위해 추가경정예산에 농업용 면세유 유가연동보조금 623억 원을 반영했는데요. 경유는 ℓ당 138.4원, 등유는 ℓ당 143.9원 등 금액 한도가 있어 농가의 생산비 부담은 여전할... ",
        "pubDate": "Wed, 06 May 2026 11:47:00 +0900",
        "formatted_date": "05월 06일, 11시 47분",
        "ai_summary": "정부가 농업용 면세유 보조금을 지원하지만, 고유가로 인한 농가의 생산비 부담은 여전히 지속되고 있음."
      },
      {
        "title": "지난달 소비자물가 1년 9개월 만 최대 상승…국제유가 영향",
        "originallink": "https://news.knn.co.kr/news/article_sns/1262",
        "link": "https://news.knn.co.kr/news/article_sns/1262",
        "description": "석유류 가격이 20% 넘게 오르는 등 중동 전쟁에 따른 국제유가 상승이 물가에 영향을 미친 것으로 분석됩니다. 국가데이터처가 6일 발표한 ‘4월 소비자물가 동향’에 따르면 지난달 소비자물가지수는 119.37로... ",
        "pubDate": "Wed, 06 May 2026 11:46:00 +0900",
        "formatted_date": "05월 06일, 11시 46분",
        "ai_summary": "중동 전쟁으로 인한 국제유가 급등 여파로 4월 소비자물가가 1년 9개월 만에 최대 상승 폭을 기록함."
      },
      {
        "title": "고유가도 비껴간 AI 랠리…코스피, '8000피' 기대감 키운다",
        "originallink": "http://www.newsian.co.kr/news/articleView.html?idxno=89294",
        "link": "http://www.newsian.co.kr/news/articleView.html?idxno=89294",
        "description": "고유가 국면과 달리 코스피가 강한 랠리를 이어갈 수 있는 가장 큰 이유는 반도체 무역수지 흑자가 원유 적자 폭을 압도하고 있기 때문&quot;이라고 분석했다. 러시아·우크라이나 전쟁 당시에는 유가 급등으로 무역수지가... ",
        "pubDate": "Wed, 06 May 2026 11:46:00 +0900",
        "formatted_date": "05월 06일, 11시 46분",
        "ai_summary": "반도체 무역수지 흑자가 원유 적자 폭을 압도하면서 고유가 상황 속에서도 코스피가 상승 랠리를 이어가고 있음."
      },
      {
        "title": "사우디, 아시아 수출 유가 4달러 인하…여전히 역대급 '할증'",
        "originallink": "https://www.news1.kr/world/middleeast-africa/6157977",
        "link": "https://n.news.naver.com/mnews/article/421/0008928477?sid=104",
        "description": "국제 유가 역시 높은 수준을 이어가고 있다. 글로벌 기준유인 브렌트유는 2월 말 전쟁 발발 이후 50% 넘게 상승했으며 최근에는 4년 만의 최고치까지 치솟았다. 미국과 이란이 호르무즈 해협 문제를 둘러싸고 대치를... ",
        "pubDate": "Wed, 06 May 2026 11:45:00 +0900",
        "formatted_date": "05월 06일, 11시 45분",
        "ai_summary": "사우디가 아시아 수출 유가를 일부 인하했으나, 전쟁 발발 이후 국제 유가는 여전히 높은 수준을 유지하고 있음."
      },
      {
        "title": "영동군, 고유가 피해지원금 '찾아가는 신청 서비스' 시행",
        "originallink": "https://www.ccdailynews.com/news/articleView.html?idxno=2414371",
        "link": "https://www.ccdailynews.com/news/articleView.html?idxno=2414371",
        "description": "충북 영동군의 고유가 피해지원금(1차) 지급률이 80%를 넘어서며 순조로운 집행 흐름을 보이고 있다. 6일... 고유가 피해지원금은 단계적으로 지급된다. 1차 지원은 취약계층을 대상으로 5월 8일까지 진행되며 2차 지원은... ",
        "pubDate": "Wed, 06 May 2026 11:44:00 +0900",
        "formatted_date": "05월 06일, 11시 44분",
        "ai_summary": "영동군이 취약계층 대상 고유가 피해지원금 1차 지급을 순조롭게 진행 중이며 현장 방문 신청 서비스를 시행함."
      },
      {
        "title": "중동 전쟁發 유가 쇼크…물가 1년9개월 만에 최대폭 상승",
        "originallink": "https://www.thepublic.kr/news/articleView.html?idxno=303401",
        "link": "https://www.thepublic.kr/news/articleView.html?idxno=303401",
        "description": "중동 전쟁에 따른 국제유가 급등 영향이 국내 소비자물가에 본격 반영되면서 지난달 물가 상승률이 크게... 유가 상승은 서비스 가격에도 영향을 미쳤다. 국제항공료 상승률은 전월 0.8%에서 15.9%로 급등했고... ",
        "pubDate": "Wed, 06 May 2026 11:44:00 +0900",
        "formatted_date": "05월 06일, 11시 44분",
        "ai_summary": "중동발 유가 쇼크가 물가 전반에 영향을 미치며 항공료 등 서비스 가격 상승과 소비자물가 급등을 초래함."
      },
      {
        "title": "유가 급락에 실적 호조까지...중동 긴장 완화 속 뉴욕증시 '최고치 질주...",
        "originallink": "https://www.thepublic.kr/news/articleView.html?idxno=303387",
        "link": "https://www.thepublic.kr/news/articleView.html?idxno=303387",
        "description": "국제유가 하락과 기업 실적 호조에 미국 뉴욕증시가 또다시 상승세를 이어갔다. 5일(현지시간)... 이에 따라 에너지 시장의 불확실성이 완화되며 국제유가는 큰 폭으로 떨어졌다. 7월 인도분 브렌트유 선물 가격은... ",
        "pubDate": "Wed, 06 May 2026 11:44:00 +0900",
        "formatted_date": "05월 06일, 11시 44분",
        "ai_summary": "국제 유가 하락과 기업 실적 호조에 힘입어 뉴욕증시가 상승세를 보이며 최고치를 경신함."
      }
    ],
    "코스피": [
      {
        "title": "정청래 &quot;코스피 7000 경이롭다…李대통령 '부동산 메시지' 효과&quot;",
        "originallink": "https://www.pressian.com/pages/articles/2026050611051876301?utm_source=naver&utm_medium=search",
        "link": "https://n.news.naver.com/mnews/article/002/0002440334?sid=100",
        "description": "돌파한 코스피 지수를 두고 &quot;이재명 대통령이 SNS를 통해 수 차례 강력한 의지를 밝혔던 부동산 시장 안정의... 정 대표는 6일 오전 국회에서 열린 당 최고위원회 모두발언에서 이날 오전 기준 7000을 돌파한 코스피 지수에... ",
        "pubDate": "Wed, 06 May 2026 11:58:00 +0900",
        "formatted_date": "05월 06일, 11시 58분",
        "ai_summary": "정청래 더불어민주당 대표가 코스피 7000 돌파가 이재명 대통령의 부동산 안정화 메시지 덕분이라고 평가했습니다."
      },
      {
        "title": "코스피 '7000시대' 열려…반도체가 견인한 신기록, 8000선 가나",
        "originallink": "https://news.jtbc.co.kr/article/NB12297144?influxDiv=NAVER",
        "link": "https://n.news.naver.com/mnews/article/437/0000490274?sid=101",
        "description": "거침없는 상승세를 보인 코스피가 사상 처음으로 7000선을 넘었습니다. 지난 2월 25일, 6000선을 넘긴 지 불과 두 달여 만입니다. 오늘(6일) 오전 코스피는 개장 직후 폭발적인 매수세가 유입되며 단숨에 7000선을... ",
        "pubDate": "Wed, 06 May 2026 11:55:00 +0900",
        "formatted_date": "05월 06일, 11시 55분",
        "ai_summary": "코스피 지수가 사상 처음으로 7000선을 돌파하며 6000선 돌파 이후 두 달여 만에 신기록을 경신했습니다."
      },
      {
        "title": "이승훈 IBK證 센터장 &quot;코스피, '1만피'도 불가능 아냐&quot;[칠천피 시대]",
        "originallink": "https://www.newsis.com/view/NISX20260506_0003618382",
        "link": "https://n.news.naver.com/mnews/article/003/0013927969?sid=101",
        "description": "최근 코스피가 사상 처음으로 7000선을 넘어선 가운데 이승훈 IBK투자증권 리서치센터장은 8000선 도달도 충분히 가능하며 '1만피(코스피 1만포인트)'도 불가능한 수준은 아니라고 내다봤다. 이 센터장은 6일 뉴시스와... ",
        "pubDate": "Wed, 06 May 2026 11:54:00 +0900",
        "formatted_date": "05월 06일, 11시 54분",
        "ai_summary": "이승훈 IBK투자증권 센터장은 코스피 7000 돌파를 축하하며 향후 8000선과 1만 포인트 도달도 가능할 것으로 전망했습니다."
      },
      {
        "title": "코스피 7천 돌파 관련 발언하는 정청래 대표",
        "originallink": "https://www.mk.co.kr/article/12037264",
        "link": "https://n.news.naver.com/mnews/article/009/0005675840?sid=100",
        "description": "코스피 7천 돌파 관련 발언하는 정청래 대표 더불어민주당 정청래 대표가 6일 국회에서 열린 최고위원회의에서 이날 개장하자 마자 7천선을 넘어선 코스피 관련 발언을 하고 있다. 2026.5.6.",
        "pubDate": "Wed, 06 May 2026 11:54:00 +0900",
        "formatted_date": "05월 06일, 11시 54분",
        "ai_summary": "정청래 더불어민주당 대표가 6일 최고위원회의에서 코스피 7000선 돌파와 관련해 발언하고 있습니다."
      },
      {
        "title": "[특징주] 삼성전자, 코스피 7000 첫 돌파에 12%대 급등…반도체 랠리 확...",
        "originallink": "https://www.tokenpost.kr/news/economy/356685",
        "link": "https://www.tokenpost.kr/news/economy/356685",
        "description": "삼성전자가 코스피 7000선 첫 돌파 흐름 속에 급등하고 있다. 현재 시세에 따르면 삼성전자는 262000원으로 전일 대비 12.69% 상승 중이다. 이번 반등은 코스피가 사상 처음 7000선을 넘어선 가운데 반도체 업종 전반으로... ",
        "pubDate": "Wed, 06 May 2026 11:54:00 +0900",
        "formatted_date": "05월 06일, 11시 54분",
        "ai_summary": "코스피 7000 돌파 흐름 속에서 반도체 업종 전반이 강세를 보이며 삼성전자 주가가 12% 이상 급등했습니다."
      },
      {
        "title": "코스피 7천 돌파 관련 발언하는 정청래 대표",
        "originallink": "https://www.mk.co.kr/article/12037262",
        "link": "https://n.news.naver.com/mnews/article/009/0005675838?sid=100",
        "description": "코스피 7천 돌파 관련 발언하는 정청래 대표 더불어민주당 정청래 대표가 6일 국회에서 열린 최고위원회의에서 이날 개장하자 마자 7천선을 넘어선 코스피 관련 발언을 하고 있다. 2026.5.6.",
        "pubDate": "Wed, 06 May 2026 11:53:00 +0900",
        "formatted_date": "05월 06일, 11시 53분",
        "ai_summary": "정청래 더불어민주당 대표가 6일 최고위원회의에서 코스피 7000 돌파에 대한 당의 입장을 밝히고 있습니다."
      },
      {
        "title": "정청래 &quot;코스피 7000은 이재명 국정신뢰 결과…국민의힘은 갈라파고스&quot;",
        "originallink": "https://www.etoday.co.kr/news/view/2581906",
        "link": "https://www.etoday.co.kr/news/view/2581906",
        "description": "이투데이=정성욱 기자 | 코스피 7257…&quot;이재명 국정신뢰가 끌어올린 결과&quot; 39년 만의 개헌안 표결, 국힘에 &quot;소신투표&quot; 호소 정청래 더불어민주당 대표가 코스피 지수 7257.88을 두고 &quot;이재명 대통령 국정 신뢰가 끌어올린... ",
        "pubDate": "Wed, 06 May 2026 11:52:00 +0900",
        "formatted_date": "05월 06일, 11시 52분",
        "ai_summary": "정청래 대표는 코스피 7257 달성이 이재명 대통령의 국정 신뢰 결과라고 강조하며 야당을 비판했습니다."
      },
      {
        "title": "국내 ETF, 450조원 육박하며 코스피 7,000 돌파에 맞춰 급성장",
        "originallink": "https://www.tokenpost.kr/news/market/356683",
        "link": "https://www.tokenpost.kr/news/market/356683",
        "description": "국내 증시가 사상 처음으로 코스피 7,000선을 넘어서면서 상장지수펀드 시장도 빠른 속도로 몸집을... 한국거래소에 따르면 2026년 5월 6일 오전 9시 1분 기준 코스피 시장에 상장된 ETF는 모두 1천99개, 시가총액은... ",
        "pubDate": "Wed, 06 May 2026 11:50:00 +0900",
        "formatted_date": "05월 06일, 11시 50분",
        "ai_summary": "코스피 7000 돌파와 함께 국내 상장지수펀드(ETF) 시장도 급성장하며 시가총액이 450조 원에 육박했습니다."
      },
      {
        "title": "코스피 7,000선 돌파…반도체 급등에 ‘7천피’ 시대 열려",
        "originallink": "https://news.knn.co.kr/news/article_sns/1264",
        "link": "https://news.knn.co.kr/news/article_sns/1264",
        "description": "코스피가 사상 처음으로 7,000선을 돌파하며 이른바 ‘7천피’ 시대를 열었습니다. 6일 한국거래소에 따르면 코스피는 장 초반 전 거래일보다 큰 폭으로 오르며 7,000선을 넘어섰습니다. 지수는 전장보다 156.02포인트... ",
        "pubDate": "Wed, 06 May 2026 11:48:00 +0900",
        "formatted_date": "05월 06일, 11시 48분",
        "ai_summary": "코스피 지수가 반도체주 급등에 힘입어 사상 처음으로 7000선을 넘어서며 '7천피' 시대를 열었습니다."
      },
      {
        "title": "꿈의 7000선 돌파…코스피, 앞으로의 향방은",
        "originallink": "https://www.mediapen.com/news/view/1097192",
        "link": "https://www.mediapen.com/news/view/1097192",
        "description": "코스피 지수가 꿈의 7000선을 돌파하면서 시장의 기대감도 커지고 있다. 미국-이란 충돌의 여파가 여전히 큰... 다만 코스피가 5% 넘게 올랐던 지난 4일 장세에서도 상승 종목보다는 하락 종목 수가 더 많았고, 비슷한... ",
        "pubDate": "Wed, 06 May 2026 11:48:00 +0900",
        "formatted_date": "05월 06일, 11시 48분",
        "ai_summary": "코스피 7000 돌파로 기대감이 커진 가운데, 향후 시장 향방과 하락 종목의 비중 등 시장 상황을 예의주시하고 있습니다."
      }
    ]
  },
  "last_updated": "2026-05-06 12:02:33"
}