{
  "pane1": [
    {
      "title": "[속보] ‘연어 술파티 의혹’ 박상용 검사 “어떻게 사실이겠나…방어...",
      "originallink": "https://www.dt.co.kr/article/12061771?ref=naver",
      "link": "https://n.news.naver.com/mnews/article/029/0003025978?sid=102",
      "description": "‘쌍방울 대북송금 사건’ 수사와 관련해 제기된 이른바 ‘연어 술 파티’ 진술 회유 의혹에 대해 박상용 인천지검 부부장검사가 대검찰청 감찰위원회에 소명할 기회를 달라며 11일 대검 청사를 방문했다. 대검은 이날... ",
      "pubDate": "Mon, 11 May 2026 14:57:00 +0900",
      "formatted_date": "05월 11일, 14시 57분",
      "ai_summary": "박상용 검사가 ‘연어 술파티’ 의혹과 관련해 대검찰청 감찰위원회에 직접 출석해 소명할 기회를 달라고 요청했습니다. 의혹의 사실 여부를 떠나 자신의 방어권을 보장해달라는 입장입니다."
    },
    {
      "title": "[속보]‘바위서 쉬다가’ 북한산 추락 40대, 헬기 이송 후 치료",
      "originallink": "https://www.munhwa.com/article/11588161?ref=naver",
      "link": "https://n.news.naver.com/mnews/article/021/0002790479?sid=102",
      "description": "경기도북부소방재난본부 제공 북한산에서 등산을 하던 40대 남성이 앉아서 쉬던 도중 5m 아래로 추락하는 사고가 발생했다. 11일 소방당국 등에 따르면 지난 10일 오후 1시쯤 경기 고양시 덕양구 북한산 용혈봉... ",
      "pubDate": "Mon, 11 May 2026 14:54:00 +0900",
      "formatted_date": "05월 11일, 14시 54분",
      "ai_summary": "북한산을 등산하던 40대 남성이 휴식 중 5m 아래로 추락하는 사고가 발생했습니다. 피해자는 헬기로 이송되어 치료를 받고 있습니다."
    },
    {
      "title": "“전쟁하라는 건가”",
      "originallink": "https://www.bigtanews.co.kr/article/view/big202605110008",
      "link": "https://www.bigtanews.co.kr/article/view/big202605110008",
      "description": "그럼 이란하고 전쟁해야겠냐?(추천 1041) 포털 네이버에서는 문화일보 5월 10일자 &lt;[속보]“나무호 사실상 피격…‘韓 건들면 패가망신’ 李어떻게 할 것인가?” 성일종 지적&gt;에 댓글 1934개, 반응 1229개가 달렸다(최신... ",
      "pubDate": "Mon, 11 May 2026 14:52:00 +0900",
      "formatted_date": "05월 11일, 14시 52분",
      "ai_summary": "성일종 의원의 이란 관련 발언에 대해 대중의 비판적 반응이 이어지고 있습니다. 온라인 커뮤니티를 중심으로 전쟁 위험을 우려하는 댓글이 다수 달렸습니다."
    },
    {
      "title": "[속보] 선도전기 VI 오후 3차례 발동, 주가 19%↑",
      "originallink": "https://www.cbci.co.kr/news/articleView.html?idxno=573648",
      "link": "https://www.cbci.co.kr/news/articleView.html?idxno=573648",
      "description": "자료사진 AI가 생성. 기사와는 무관함. 11일 오후 선도전기(007610)의 VI가 3차례 발동됐다. VI는 오후 2시와 2시 3분, 2시 40분에 각각 발동됐다. 앞서 오전장에서도 VI가 발동되기도 했다. 오전 9시 13분경 발동됐다가... ",
      "pubDate": "Mon, 11 May 2026 14:46:00 +0900",
      "formatted_date": "05월 11일, 14시 46분",
      "ai_summary": "선도전기 주가가 급등하며 오후에만 VI가 세 차례 발동되었습니다. 당일 오전장에도 한 차례 VI가 발동된 바 있습니다."
    },
    {
      "title": "[속보] 씨메스로보틱스, 쿠팡풀필먼트서비스와 69억원 규모 물류 로봇 ...",
      "originallink": "https://www.cbci.co.kr/news/articleView.html?idxno=573643",
      "link": "https://www.cbci.co.kr/news/articleView.html?idxno=573643",
      "description": "씨메스 자료사진. CBC뉴스 DB. 씨메스로보틱스는 쿠팡풀필먼트서비스 유한회사와 69억1000만원 규모의 물류 로봇 자동화 솔루션 설치 공급계약을 체결했다고 11일 공시했다. 계약금액은 최근 매출액 대비 52.93%에... ",
      "pubDate": "Mon, 11 May 2026 14:42:00 +0900",
      "formatted_date": "05월 11일, 14시 42분",
      "ai_summary": "씨메스로보틱스가 쿠팡풀필먼트서비스와 69억 원 규모의 물류 로봇 공급계약을 체결했습니다. 이는 최근 매출액의 50%를 넘는 큰 규모입니다."
    },
    {
      "title": "[속보] '연어 술파티 의혹' 박상용 &quot;감찰위, 방어권·소명 기회 보장해야...",
      "originallink": "https://www.cjb.co.kr/home/sub.php?menukey=61&mod=view&P_NO=260511503&PRO_CODE=99",
      "link": "https://n.news.naver.com/mnews/article/655/0000030919?sid=102",
      "description": "쌍방울 대북송금 사건 수사 과정에서 불거진 '연어 술파티 진술 회유 의혹'으로 감찰을 받고 있는 박상용 검사가 대검찰청 감찰위원회에 직접 출석해 소명할 수 있게 해달라고 호소에 나섰습니다. 박 검사는 11일 오후... ",
      "pubDate": "Mon, 11 May 2026 14:41:00 +0900",
      "formatted_date": "05월 11일, 14시 41분",
      "ai_summary": "박상용 검사가 대검찰청 감찰위에 출석해 진술 회유 의혹에 대한 소명 기회를 요구했습니다. 자신에 대한 감찰 과정에서 공정한 방어권 보장을 촉구했습니다."
    },
    {
      "title": "[속보] 대구 팔공산 화재···헬기 8대 동원해 1시간여 만에 큰불 꺼",
      "originallink": "https://dgmbc.com/NewsArticle/839701",
      "link": "https://n.news.naver.com/mnews/article/657/0000051326?sid=102",
      "description": "5월 11일 낮 12시 49분쯤 대구 동구 도학동 팔공산에서 불이 나 1시간 2분 만에 큰불이 꺼졌습니다. 산림 당국은 헬기 8대, 차량 39대, 인력 143명을 동원해 낮 1시 51분쯤 큰불을 껐습니다. 또 잔불을 정리하는 대로... ",
      "pubDate": "Mon, 11 May 2026 14:38:00 +0900",
      "formatted_date": "05월 11일, 14시 38분",
      "ai_summary": "대구 팔공산에서 발생한 화재가 헬기 8대와 인력 143명이 투입된 끝에 1시간 만에 진화됐습니다. 현재 당국은 잔불 정리를 진행 중입니다."
    },
    {
      "title": "[속보] '마약왕' 박왕열 공급책 '청담' 국내송환 열흘만에 구속 송치",
      "originallink": "https://www.kado.net/news/articleView.html?idxno=2049418",
      "link": "https://n.news.naver.com/mnews/article/654/0000179895?sid=102",
      "description": "'필리핀 마약총책'으로 불린 박왕열에게 마약류를 공급한 혐의를 받는 마약사범 '청담'이 국내 송환 열흘 만에 검찰에 넘겨졌다. 경기남부경찰청 마약범죄수사대는 11일 특정범죄 가중처벌 등에 관한 법률 위반(향정)과... ",
      "pubDate": "Mon, 11 May 2026 14:33:00 +0900",
      "formatted_date": "05월 11일, 14시 33분",
      "ai_summary": "필리핀 마약왕 박왕열에게 마약을 공급한 혐의를 받는 '청담'이 국내 송환 열흘 만에 구속 송치되었습니다. 경찰은 관련 혐의에 대해 수사를 이어가고 있습니다."
    },
    {
      "title": "[속보] &quot;정신과 약물 60정 빻아 술에 타고 살해 시도&quot; 경찰, 부천 태권도...",
      "originallink": "https://www.imaeil.com/page/view/2026051114065205602",
      "link": "https://n.news.naver.com/mnews/article/088/0001009320?sid=102",
      "description": "술에 약물을 타 남편을 살해하려 한 태권도장 직원과 공범인 관장의 범행동기 확인을 위해 경찰이 강제수사에 나선다. 경기남부경찰청은 11일 정례간담회에서 &quot;살인미수 혐의로 구속된 태권도장 관장 A(20대·여)씨와... ",
      "pubDate": "Mon, 11 May 2026 14:33:00 +0900",
      "formatted_date": "05월 11일, 14시 33분",
      "ai_summary": "남편을 살해하려 약물을 탄 혐의를 받는 태권도장 관장과 직원의 범행 동기를 확인하기 위해 경찰이 강제수사에 착수했습니다. 현재 두 사람은 살인미수 혐의로 구속 상태입니다."
    },
    {
      "title": "[속보] 9살인 친딸 10년간 성폭행…학생까지 추행한 50대 남성 ‘징역 1...",
      "originallink": "https://www.seoul.co.kr/news/society/law/2026/05/11/20260511500144?wlog_tag3=naver",
      "link": "https://n.news.naver.com/mnews/article/081/0003642658?sid=102",
      "description": "어린 딸을 10년간 성폭행하고 학원 강사로 일하면서 학생까지 추행한 50대 남성에게 중형이 선고됐다. 11일 뉴스1에 따르면 대전지법 천안지원 제1형사부(부장 조영진)는 아동·청소년의 성보호에 관한 법률 위반(위계 등... ",
      "pubDate": "Mon, 11 May 2026 14:28:00 +0900",
      "formatted_date": "05월 11일, 14시 28분",
      "ai_summary": "친딸을 10년간 성폭행하고 제자까지 추행한 50대 남성에게 중형이 선고되었습니다. 재판부는 아동·청소년 대상 성범죄의 심각성을 고려해 판결했습니다."
    },
    {
      "title": "[속보] 한전KPS, 1분기 잠정 영업이익 370억원…전년比 374.6% 증가",
      "originallink": "https://www.cbci.co.kr/news/articleView.html?idxno=573634",
      "link": "https://www.cbci.co.kr/news/articleView.html?idxno=573634",
      "description": "자료사진 기사와는 무관함. AI가 생성. 한전KPS는 2026년 1분기 연결 기준 잠정 영업이익이 370억1800만원으로 전년 동기 대비 374.59% 증가했다고 11일 공시했다. 같은 기간 매출액은 3523억9400만원으로 전년 동기... ",
      "pubDate": "Mon, 11 May 2026 14:26:00 +0900",
      "formatted_date": "05월 11일, 14시 26분",
      "ai_summary": "한전KPS가 2026년 1분기 잠정 영업이익 370억 원을 기록하며 전년 동기 대비 약 374.6% 급증했다. 매출액 또한 3523억 원을 달성하며 성장세를 보였다."
    },
    {
      "title": "[속보]경찰 ‘노조 블랙리스트’ 의혹 삼전기흥사업장 압색",
      "originallink": "https://www.munhwa.com/article/11588153?ref=naver",
      "link": "https://n.news.naver.com/mnews/article/021/0002790471?sid=102",
      "description": "연합뉴스 삼성전자 내부에서 노동조합 가입 여부가 담긴 이른바 ‘노조 블랙리스트’가 작성됐다는 의혹과 관련해 경찰이 11일 삼성전자 기흥사업장을 압수수색했다. 앞서 삼성전자는 지난달 16일 직원 개인정보를... ",
      "pubDate": "Mon, 11 May 2026 14:16:00 +0900",
      "formatted_date": "05월 11일, 14시 16분",
      "ai_summary": "삼성전자 내부 노조 블랙리스트 작성 의혹과 관련해 경찰이 삼성전자 기흥사업장을 압수수색했다. 앞서 삼성전자는 개인정보 유출 논란을 겪은 바 있다."
    },
    {
      "title": "[속보] ‘대북송금 의혹 수사’ 박상용 검사 “‘연어·술 파티’ 사실...",
      "originallink": "https://www.khan.co.kr/article/202605111412001",
      "link": "https://n.news.naver.com/mnews/article/032/0003444969?sid=102",
      "description": "쌍방울 대북송금 의혹 사건 검찰 수사 당시 ‘연어·술 파티’로 핵심 피의자를 회유했다는 의혹을 받는 박상용 인천지검 부부장검사가 대검찰청 감찰위원회를 앞두고 대검 청사를 찾아 “해명 기회를 달라”고 밝혔다.... ",
      "pubDate": "Mon, 11 May 2026 14:12:00 +0900",
      "formatted_date": "05월 11일, 14시 12분",
      "ai_summary": "대북송금 의혹 수사 당시 회유 의혹을 받은 박상용 검사가 대검찰청 감찰위원회를 앞두고 직접 해명 기회를 요구하며 입장을 밝혔다."
    },
    {
      "title": "[속보]SK하이닉스, 193만원 터치…삼전도 28만8500원으로 최고가",
      "originallink": "https://www.mt.co.kr/stock/2026/05/11/2026051114081025540",
      "link": "https://n.news.naver.com/mnews/article/008/0005355693?sid=101",
      "description": "11일 장 중 SK하이닉스와 삼성전자가 각각 193만3000원과 28만8500원까지 오르며 사상 최고치를 경신했다.",
      "pubDate": "Mon, 11 May 2026 14:09:00 +0900",
      "formatted_date": "05월 11일, 14시 09분",
      "ai_summary": "SK하이닉스와 삼성전자가 장중 각각 193만 3000원과 28만 8500원까지 오르며 사상 최고가를 나란히 경신했다."
    },
    {
      "title": "2% 후반대로 오르는 성장률 기대치…KDI·한은도 상향하나",
      "originallink": "https://www.asiatime.co.kr/article/20260511500242",
      "link": "https://www.asiatime.co.kr/article/20260511500242",
      "description": "한은에 따르면 1분기 GDP 성장률(속보)은 중동발 지정학적 불확실성 속에서도 민간 소비가 버텨주고 반도체 등 수출 호조가 성장세를 견인하며 전분기대비 1.7% 깜짝 성장했다. 정보기술(IT) 품목을 중심으로 한 수출... ",
      "pubDate": "Mon, 11 May 2026 14:08:00 +0900",
      "formatted_date": "05월 11일, 14시 08분",
      "ai_summary": "수출 호조와 민간 소비에 힘입어 1분기 GDP가 1.7% 깜짝 성장하며, 경제 성장률 전망치 상향 조정 가능성이 제기되고 있다."
    }
  ],
  "pane2": {
    "산업부": [
      {
        "title": "&quot;세계 5위 경제대국 인도 잡아라&quot;…산업부, 공급망 협력 전문가 간담회",
        "originallink": "https://view.asiae.co.kr/article/2026051113432022026",
        "link": "https://n.news.naver.com/mnews/article/277/0005760934?sid=101",
        "description": "산업부는 이번 간담회에서 제기된 의견을 정책에 반영해 한-인도 산업협력의 실행력을 높이고, 정상외교 성과가 조기에 가시화될 수 있도록 관계부처 및 유관기관과 협력을 강화할 계획이다.",
        "pubDate": "Mon, 11 May 2026 13:43:00 +0900",
        "formatted_date": "05월 11일, 13시 43분",
        "ai_summary": "산업부가 세계 5위 경제 대국 인도를 겨냥해 공급망 협력 전문가 간담회를 개최했다. 논의된 의견을 바탕으로 한-인도 간 산업 협력 성과를 조기에 가시화할 방침이다."
      },
      {
        "title": "산업부, 한국-방글라데시 탄소시장 협력…투자 연계 모색",
        "originallink": "https://www.newsis.com/view/NISX20260511_0003623608",
        "link": "https://n.news.naver.com/mnews/article/003/0013936694?sid=101",
        "description": "11일 산업부는 이날부터 14일까지 나흘간 방글라데시 정부 관계자를 한국으로 초청해 파리협정 제 6조 기반... 이번 연수는 지난해 6월 체결된 산업부·환경산림기후변화부 간 파리협정 제 6조 이행 양해각서(MOU)의 후속... ",
        "pubDate": "Mon, 11 May 2026 11:00:00 +0900",
        "formatted_date": "05월 11일, 11시 00분",
        "ai_summary": "산업부가 방글라데시 정부 관계자를 초청해 파리협정 제6조에 기반한 탄소시장 협력 및 투자 연계 방안을 논의했다."
      },
      {
        "title": "산업부, 방글라데시 공무원 초청연수…&quot;탄소시장 협력&quot;",
        "originallink": "https://www.yna.co.kr/view/AKR20260511051900003?input=1195m",
        "link": "https://n.news.naver.com/mnews/article/001/0016069134?sid=101",
        "description": "이번 연수는 파리협정 제6조에 기반한 탄소시장 협력, 국제감축사업 발굴 기반을 마련하기 위한 것으로 산업부와 방글라데시 환경산림기후변화부가 2024년 6월 체결한 양해각서(MOU)의 후속 조치다. 방글라데시 환경부... ",
        "pubDate": "Mon, 11 May 2026 11:00:00 +0900",
        "formatted_date": "05월 11일, 11시 00분",
        "ai_summary": "산업부가 방글라데시 공무원 대상 연수를 통해 국제감축사업 발굴과 탄소시장 협력을 구체화한다. 이는 양국 간 체결된 MOU의 후속 조치다."
      },
      {
        "title": "산업부, 인도와 산업·공급망 협력 확대 방안 논의",
        "originallink": "https://www.newsis.com/view/NISX20260511_0003623602",
        "link": "https://n.news.naver.com/mnews/article/003/0013936696?sid=101",
        "description": "산업부 관계자는 &quot;간담회에서 제기된 의견을 정책에 적극 반영하여 한-인도 산업 협력의 실행력을 높이고, 국빈 방문 성과가 조속히 가시화될 수 있도록 관계부처 및 유관기관과 긴밀히 협력해 나갈 계획&quot;이라고 전했다.",
        "pubDate": "Mon, 11 May 2026 11:00:00 +0900",
        "formatted_date": "05월 11일, 11시 00분",
        "ai_summary": "산업부가 인도와의 산업 및 공급망 협력을 강화하기 위해 간담회를 열었다. 수렴된 정책 의견을 반영해 양국 간 협력의 실행력을 높일 계획이다."
      },
      {
        "title": "산업부, '세계 5위' 경제대국 인도와 경제협력 확대…수출 다변화 박차",
        "originallink": "https://www.newspim.com/news/view/20260511000309",
        "link": "https://www.newspim.com/news/view/20260511000309",
        "description": "산업부는 &quot;이번 간담회에서 제기된 의견을 정책에 적극 반영해 한-인도 산업 협력의 실행력을 높이고, 국빈 방문 성과가 조속히 가시화될 수 있도록 관계부처 및 유관기관과 긴밀히 협력해 나갈 계획&quot;이라고 밝혔다.",
        "pubDate": "Mon, 11 May 2026 11:00:00 +0900",
        "formatted_date": "05월 11일, 11시 00분",
        "ai_summary": "산업부가 경제 대국 인도와의 협력 확대로 수출 다변화를 추진한다. 관계부처와의 긴밀한 협력을 통해 정상외교 성과를 신속히 실현할 예정이다."
      },
      {
        "title": "마스오토, 산업부 지원 기반 미국 자율주행 트럭 사업 가속화",
        "originallink": "https://www.discoverynews.kr/news/articleView.html?idxno=1090912",
        "link": "https://www.discoverynews.kr/news/articleView.html?idxno=1090912",
        "description": "마스오토는 산업부 산하 한국산업기술진흥원(KIAT)의 '규제특례 신산업창출' 사업 대상자로 선정되어 향후 2년간 20억 원 규모의 연구개발(R&amp;D) 자금을 지원받게 됐다. 해당 사업은 규제특례 실증을 마친 신산업의 후속... ",
        "pubDate": "Mon, 11 May 2026 10:18:00 +0900",
        "formatted_date": "05월 11일, 10시 18분",
        "ai_summary": "자율주행 트럭 기업 마스오토가 산업부의 규제특례 신산업창출 사업 대상자로 선정되었습니다. 이를 통해 향후 2년간 20억 원 규모의 연구개발 자금을 지원받아 미국 사업을 가속화합니다."
      },
      {
        "title": "산업부, '비정상 관행' 개선 본격 착수...산업·통상·자원 분야 정상화...",
        "originallink": "https://www.ilyoseoul.co.kr/news/articleView.html?idxno=516823",
        "link": "https://www.ilyoseoul.co.kr/news/articleView.html?idxno=516823",
        "description": "산업부는 5월 8일 문신학 차관 주재로 TF 1차 회의를 열고, 불법·불량제품 유통 차단, 온라인 원산지 표시 정비... 산업부는 사전 브레인스토밍과 국민제안 창구를 통해 후보 과제를 발굴했으며, 이날 회의에는 외부... ",
        "pubDate": "Mon, 11 May 2026 08:58:00 +0900",
        "formatted_date": "05월 11일, 08시 58분",
        "ai_summary": "산업부가 불법·불량제품 유통 차단 등 비정상적 관행을 개선하기 위한 본격적인 정상화 작업에 착수했습니다. TF를 구성하고 국민 제안 등을 통해 과제를 발굴할 예정입니다."
      },
      {
        "title": "산업부 장관, 한미 전략적 투자·에너지 협력 강화 논의",
        "originallink": "https://www.todayenergy.kr/news/articleView.html?idxno=297595",
        "link": "https://www.todayenergy.kr/news/articleView.html?idxno=297595",
        "description": "산업부에 따르면, 김정관 장관은 방문 기간 중 하워드 러트닉 미 상무부 장관을 만나 대미투자특별법의 후속... 또한 산업부와 미 상무부는 '한-미 조선 파트너십 이니셔티브'에 관한 양해각서(MOU)를 체결하고 '한미... ",
        "pubDate": "Mon, 11 May 2026 08:40:00 +0900",
        "formatted_date": "05월 11일, 08시 40분",
        "ai_summary": "산업부 장관이 미국 상무부 장관과 만나 전략적 투자 및 에너지 협력을 논의했습니다. 특히 한-미 조선 파트너십 이니셔티브에 관한 MOU를 체결하는 등 협력을 강화했습니다."
      },
      {
        "title": "대미 조선업 협력 '마스가' 본격화…산업부 &quot;대미 투자 1호는 지켜봐달...",
        "originallink": "https://www.news1.kr/economy/idustry-trade/6162018",
        "link": "https://n.news.naver.com/mnews/article/421/0008936149?sid=101",
        "description": "산업부 관계자는 &quot;대미 투자 1호 프로젝트는 아직 정해진 것은 없다&quot;며 &quot;대미투자 프로젝트 논의 과정에서 상업적 합리성 확보를 위해 최선을 다하겠다&quot;고 밝혔다. 양국 이해 맞는 '마스가'는 빠르게 진행…워싱턴에 협력... ",
        "pubDate": "Sun, 10 May 2026 19:55:00 +0900",
        "formatted_date": "05월 10일, 19시 55분",
        "ai_summary": "미국과의 조선업 협력이 본격화되는 가운데, 산업부는 대미 투자 1호 프로젝트에 대해 신중한 입장을 보였습니다. 상업적 합리성을 최우선으로 고려해 추진할 계획입니다."
      }
    ],
    "KIAT": [
      {
        "title": "램리서치, 반도체 공정설계 인재 키운다…KSIA·KIAT와 협력",
        "originallink": "http://www.inews24.com/view/1967312",
        "link": "https://n.news.naver.com/mnews/article/031/0001027731?sid=105",
        "description": "미국 반도체 장비기업 램리서치가 한국반도체산업협회(KSIA), 한국산업기술진흥원(KIAT)과 손잡고 반도체 공정설계 인재 양성에 나선다. 램리서치는 11일 KSIA·KIAT와 협력해 반도체 공정설계 전문가 양성 과정을... ",
        "pubDate": "Mon, 11 May 2026 14:51:00 +0900",
        "formatted_date": "05월 11일, 14시 51분",
        "ai_summary": "램리서치가 국내 반도체 인재 양성을 위해 한국반도체산업협회 및 한국산업기술진흥원과 협력합니다. 반도체 공정설계 전문가 양성 과정을 통해 기술 경쟁력을 강화할 방침입니다."
      },
      {
        "title": "KIAT, 국제 공동 R&amp;D 협력 통해 K첨단바이오 유럽 진출 지원",
        "originallink": "https://www.busan.com/view/busan/view.php?code=2026050620292182930",
        "link": "https://n.news.naver.com/mnews/article/082/0001379502?sid=101",
        "description": "한국산업기술진흥원(KIAT, 원장 전윤종)이 한국과 유럽 간 국제공동 연구개발(R&amp;D) 협력을 통해 국내 의료·바이오 기업의 첨단기술 확보와 해외 시장 진출을 지원한다. KIAT는 6일(현지시간) 스위스 바젤에서 열린... ",
        "pubDate": "Wed, 06 May 2026 20:36:00 +0900",
        "formatted_date": "05월 06일, 20시 36분",
        "ai_summary": "한국산업기술진흥원(KIAT)이 한-유럽 국제공동 R&D 협력을 통해 국내 바이오 기업의 기술 확보를 지원합니다. 스위스 바젤에서 열린 행사를 기점으로 유럽 시장 진출을 돕습니다."
      },
      {
        "title": "K-의료·바이오 유럽진출 돕는다…KIAT, 국제공동 R&amp;D 지원",
        "originallink": "http://www.kookje.co.kr/news2011/asp/newsbody.asp?code=0200&key=20260506.99099001115",
        "link": "https://n.news.naver.com/mnews/article/658/0000143049?sid=101",
        "description": "한국산업기술진흥원(KIAT)이 한-유럽 간 국제공동 연구개발(R&amp;D) 협력을 통해 국내 의료·바이오 기업의 첨단 기술 확보와 해외 시장 진출을 지원한다. KIAT는 6일(현지시간) 스위스 바젤에서 열린 ‘유레카 글로벌... ",
        "pubDate": "Wed, 06 May 2026 15:53:00 +0900",
        "formatted_date": "05월 06일, 15시 53분",
        "ai_summary": "KIAT가 유레카 글로벌 행사 등을 통해 국내 의료·바이오 기업의 유럽 시장 진출을 적극 지원합니다. 국제 공동 연구개발 협력을 통해 국내 기업의 글로벌 경쟁력 확보를 도모합니다."
      },
      {
        "title": "KIAT, 유럽 산학연과 바이오 공동R&amp;D 확대…국내 기업 진출 지원",
        "originallink": "https://news.tf.co.kr/read/economy/2319767.htm",
        "link": "https://n.news.naver.com/mnews/article/629/0000496858?sid=101",
        "description": "유레카 서밋 참가…한-스위스 기술협력 상담 추진 한국산업기술진흥원(KIAT)이 유럽 산학연과의 공동 연구개발(R&amp;D) 협력을 확대하며 국내 의료·바이오 기업의 해외 진출 지원에 속도를 내고 있다. KIAT는 6일(현지시각)... ",
        "pubDate": "Wed, 06 May 2026 11:01:00 +0900",
        "formatted_date": "05월 06일, 11시 01분",
        "ai_summary": "KIAT가 유럽 산학연과의 공동 연구개발 협력을 확대하며 국내 바이오 기업의 해외 진출을 지원합니다. 유레카 서밋 참여를 통해 한-스위스 간 기술 협력 상담도 함께 추진 중입니다."
      },
      {
        "title": "KIAT, 韓바이오 기업 '국제공동 R&amp;D' 파트너 발굴 지원",
        "originallink": "https://www.newsis.com/view/NISX20260506_0003617867",
        "link": "https://n.news.naver.com/mnews/article/003/0013927707?sid=101",
        "description": "한국산업기술진흥원(KIAT)이 한-유럽 간 국제공동 연구개발(R&amp;D) 협력을 통해 국내 의료·바이오 기업의 첨단 기술 확보와 해외 시장 진출을 지원한다. KIAT는 6일(현지 시간) 스위스 바젤에서 열린 '유레카 글로벌... ",
        "pubDate": "Wed, 06 May 2026 11:00:00 +0900",
        "formatted_date": "05월 06일, 11시 00분",
        "ai_summary": "KIAT가 국내 바이오 기업들이 유럽 내 공동 연구개발 파트너를 발굴할 수 있도록 적극 지원합니다. 기술 확보와 글로벌 생태계 진입을 통해 기업들의 유럽 진출을 돕습니다."
      },
      {
        "title": "KIAT, K-바이오 유럽 진출·R&amp;D 지원",
        "originallink": "https://view.asiae.co.kr/article/2026050610124027163",
        "link": "https://n.news.naver.com/mnews/article/277/0005758791?sid=101",
        "description": "KIAT)이 국내 의료·바이오 기업의 유럽 시장 진출과 첨단 기술 확보를 위한 국제공동 연구개발(R&amp;D) 지원에 나섰다. 유럽 연구기관 및 기업과의 협력을 통해 글로벌 바이오 생태계 진입을 확대하겠다는 구상이다. KIAT는... ",
        "pubDate": "Wed, 06 May 2026 10:12:00 +0900",
        "formatted_date": "05월 06일, 10시 12분",
        "ai_summary": "KIAT가 국내 의료·바이오 기업의 첨단 기술 확보와 유럽 시장 진출을 위한 R&D 지원에 나섰습니다. 유럽 기업 및 연구기관과의 협력망을 넓혀 글로벌 생태계 진입을 가속화합니다."
      },
      {
        "title": "전윤종 KIAT 원장 &quot;내년 베트남에 광물 기술협력센터 설립&quot;",
        "originallink": "https://view.asiae.co.kr/article/2026042914283869102",
        "link": "https://n.news.naver.com/mnews/article/277/0005756595?sid=101",
        "description": "한국산업기술진흥원(KIAT·원장 전윤종)이 내년 베트남 하노이에 핵심 광물 공급망 기술협력센터(이하 센터)... KIAT는 센터가 마련되면 ▲광물을 다룰 전문 인력에 대한 교육과정을 현지 개설하고 ▲광물 고부가가치화에... ",
        "pubDate": "Wed, 29 Apr 2026 14:28:00 +0900",
        "formatted_date": "04월 29일, 14시 28분",
        "ai_summary": "한국산업기술진흥원(KIAT)이 내년 베트남 하노이에 핵심 광물 기술협력센터를 설립합니다.\n현지 전문 인력 양성과 광물 고부가가치화를 위한 기술 협력을 추진할 계획입니다."
      }
    ],
    "기후부": [
      {
        "title": "'하천 제방부터 전력시설까지'…기후부, 여름철 홍수 대응 점검 나선다",
        "originallink": "https://www.electimes.com/news/articleView.html?idxno=367883",
        "link": "https://www.electimes.com/news/articleView.html?idxno=367883",
        "description": "이번 회의는 '대한민국 홍수안전강조기간' 일정으로, 금한승 기후부 1차관이 주재했으며 기상청과 유역... 특히 올해는 기후부 출범 이후 처음 맞는 여름철이라는 점에서 에너지 분야 대응 체계 점검도 포함됐다. 한수원과... ",
        "pubDate": "Mon, 11 May 2026 14:24:00 +0900",
        "formatted_date": "05월 11일, 14시 24분",
        "ai_summary": "기후부가 출범 후 첫 홍수기를 맞아 여름철 홍수 대응 점검 회의를 개최했습니다.\n하천 제방은 물론 한수원 등 에너지 시설의 재난 대응 체계까지 종합적으로 점검했습니다."
      },
      {
        "title": "기후부, 소속·산하기관과 '홍수대응' 점검 회의",
        "originallink": "https://www.nocutnews.co.kr/news/6515123?utm_source=naver&utm_medium=article&utm_campaign=20260511020555",
        "link": "https://n.news.naver.com/mnews/article/079/0004145516?sid=103",
        "description": "특히, 올해는 기후부 출범 후 처음으로 맞는 여름철로 한국수력원자력, 한국전력공사 등 에너지 관련... 금 차관은 &quot;에너지 분야 산하기관은 기후부 체계에서 홍수대응 업무를 처음 수행하는 만큼, 피해 예방을 위해... ",
        "pubDate": "Mon, 11 May 2026 14:06:00 +0900",
        "formatted_date": "05월 11일, 14시 06분",
        "ai_summary": "기후부가 산하기관과 함께 여름철 홍수 대응을 위한 점검 회의를 실시했습니다.\n에너지 분야 기관들에게 체계적인 홍수 피해 예방 업무 수행을 당부했습니다."
      },
      {
        "title": "[게시판] 기후부, 여름 홍수기 대응체계 최종 점검 회의",
        "originallink": "https://www.yna.co.kr/view/AKR20260511096900530?input=1195m",
        "link": "https://n.news.naver.com/mnews/article/001/0016069680?sid=102",
        "description": "올해 홍수기(6월 21일부터 9월 20일)는 기후부 출범 후 첫 홍수기로, 이번 회의에는 한국수력원자력과 한국전력공사 등 에너지 관련 기관도 참여, 발전 댐과 전력시설 피해 관리 계획도 논의했다. (서울=연합뉴스)",
        "pubDate": "Mon, 11 May 2026 14:00:00 +0900",
        "formatted_date": "05월 11일, 14시 00분",
        "ai_summary": "기후부가 출범 후 첫 홍수기(6월~9월)를 대비해 에너지 기관들과 최종 점검 회의를 가졌습니다.\n발전 댐과 주요 전력시설에 대한 철저한 관리 계획을 논의했습니다."
      },
      {
        "title": "기후부 출범 뒤 첫 홍수기…하천·댐·전력시설 점검",
        "originallink": "https://www.news1.kr/society/environment/6162658",
        "link": "https://n.news.naver.com/mnews/article/421/0008937338?sid=101",
        "description": "이번 회의는 '대한민국 홍수안전강조기간' 일정으로, 금한승 기후부 1차관이 주재했다. 회의에는 기상청과... 특히 올해는 기후부 출범 이후 처음 맞는 여름철이라는 점에서 에너지 분야 대응 체계 점검도 포함됐다.... ",
        "pubDate": "Mon, 11 May 2026 14:00:00 +0900",
        "formatted_date": "05월 11일, 14시 00분",
        "ai_summary": "기후부가 첫 홍수기를 앞두고 하천, 댐, 전력시설 등에 대한 안전 점검에 나섰습니다.\n기상청 및 에너지 관계기관과 협력해 여름철 재난 대응 체계를 확립할 방침입니다."
      },
      {
        "title": "'에어컨 남은 냉매 수거해 재활용'…기후부, 시범사업 실시",
        "originallink": "https://news.tvchosun.com/site/data/html_dir/2026/05/11/2026051190209.html",
        "link": "https://n.news.naver.com/mnews/article/448/0000610389?sid=102",
        "description": "기후부는 이번 시범사업 결과를 토대로 '냉매관리법'을 제정할 계획이다. 현재 냉매로 많이 사용되는 수소불화탄소(HFCs)는 '프레온가스'로 불리는 오존층 파괴 물질 염화불화탄소(CFCs)와 수소염화불화탄소(HCFCs)를... ",
        "pubDate": "Mon, 11 May 2026 13:39:00 +0900",
        "formatted_date": "05월 11일, 13시 39분",
        "ai_summary": "기후부가 온실가스인 폐냉매를 회수해 재활용하는 시범사업을 실시합니다.\n이번 결과를 토대로 향후 '냉매관리법' 제정을 추진할 계획입니다."
      },
      {
        "title": "기후부, 화학물질 등록 관련 분쟁조정제도 시행",
        "originallink": "https://www.busan.com/view/busan/view.php?code=2026051113312748929",
        "link": "https://n.news.naver.com/mnews/article/082/0001380093?sid=101",
        "description": "화학물질로 기후부 장관이 고용노동부 장관과 협의해 고시한 물질'과 '1991년 2월 2일 이후 종전 유해화학물질 관리법에 따라 유해성 심사를 받은 물질로 기후부 장관이 고시한 물질'이며 이외 화학물질은 모두 신규... ",
        "pubDate": "Mon, 11 May 2026 13:32:00 +0900",
        "formatted_date": "05월 11일, 13시 32분",
        "ai_summary": "기후부가 화학물질 등록 과정에서 발생하는 기업 간 갈등 해결을 위해 분쟁조정제도를 시행합니다.\n관련 법령에 따라 등록 자료의 비용 분담 등을 조정할 근거가 마련되었습니다."
      },
      {
        "title": "“폐냉매 그냥 버리면 지구온난화”…기후부, '회수·재생' 전주기 관리...",
        "originallink": "https://www.etnews.com/20260511000236",
        "link": "https://n.news.naver.com/mnews/article/030/0003426076?sid=101",
        "description": "기후부는 향후 이러한 냉매 전주기 관리 내용을 담은 '냉매관리법(가칭)' 제정도 추진할 계획이다. 이번... 김진식 기후부 대기환경국장은 “수소불화탄소 냉매는 한번 충전되면 15년 이상 장기적으로 누출돼 국가온실가... ",
        "pubDate": "Mon, 11 May 2026 12:18:00 +0900",
        "formatted_date": "05월 11일, 12시 18분",
        "ai_summary": "기후부가 온실가스 배출 주범인 폐냉매를 전주기적으로 관리하는 체계를 구축합니다.\n냉매의 회수부터 재생, 폐기까지 관리하는 가칭 '냉매관리법' 제정을 추진할 예정입니다."
      },
      {
        "title": "화학물질 등록 지연 막는다...기후부, 기업 간 분쟁 조정 창구 마련",
        "originallink": "https://www.ajunews.com/view/20260510102618840",
        "link": "https://www.ajunews.com/view/20260510102618840",
        "description": "기후부, 화학물질등록 관련 분쟁 조정제도 시행 아주경제=최예지 기자 ruizhi@ajunews.com 기업 간 비용 갈등으로... 기후부는 등록신청자료의 생산·활용 시 적용가능한 비용분담 및 비용계상 원칙을 관련 법률에 마련하고 분쟁... ",
        "pubDate": "Mon, 11 May 2026 12:02:00 +0900",
        "formatted_date": "05월 11일, 12시 02분",
        "ai_summary": "기후부가 화학물질 등록 자료 공유와 관련한 비용 갈등을 해소하기 위해 분쟁 조정 창구를 마련했습니다.\n기업 간 분쟁을 신속히 조정하고 관련 법률에 비용 분담 원칙을 명확히 할 계획입니다."
      },
      {
        "title": "폐냉매 다시 쓴다…기후부, 냉매 전주기 관리 시범사업 착수",
        "originallink": "https://www.news1.kr/society/environment/6162390",
        "link": "https://n.news.naver.com/mnews/article/421/0008937080?sid=101",
        "description": "회수된 폐냉매는 수분과 오염물질 제거 과정을 거쳐 신품 수준 품질의 재생냉매로 재활용된다. 기후부는 냉매 사용부터 회수·재생·폐기까지 관리하는 내용을 담은 '냉매관리법' 제정도 추진할 계획이다.",
        "pubDate": "Mon, 11 May 2026 12:00:00 +0900",
        "formatted_date": "05월 11일, 12시 00분",
        "ai_summary": "기후부가 폐냉매를 정제해 재생냉매로 재활용하는 전주기 관리 시범사업에 착수했습니다.\n사용부터 폐기까지 체계적으로 관리하기 위해 냉매관리법 제정도 추진합니다."
      },
      {
        "title": "기후부·환경공단, '폐냉매 다시 쓰는' 냉매 전주기 관리 시범사업 추진",
        "originallink": "https://www.busan.com/view/busan/view.php?code=2026051109543340948",
        "link": "https://n.news.naver.com/mnews/article/082/0001380087?sid=101",
        "description": "기후부와 환경공단은 12일 오전 ‘냉매 전주기 관리체계 구축 시범사업’ 착수보고회를 개최한다고 밝혔다. 이번 시범사업은 냉매사용기기·제품 등에서 냉매를 회수하고, 회수된 냉매를 재생하여 재사용하는 전주기... ",
        "pubDate": "Mon, 11 May 2026 12:00:00 +0900",
        "formatted_date": "05월 11일, 12시 00분",
        "ai_summary": "기후부와 환경공단이 냉매의 회수부터 재생, 재사용까지 관리하는 전주기 시범사업을 추진합니다.\n냉매 사용 기기에서 발생하는 온실가스를 줄이고 자원 순환 체계를 구축할 계획입니다."
      }
    ],
    "산업혁신기반구축": []
  },
  "pane3": {
    "호르무즈": [
      {
        "title": "李-다카이치, 19일 안동 방문 조율…'호르무즈·에너지' 협력 모색",
        "originallink": "http://www.inews24.com/view/1967363",
        "link": "https://n.news.naver.com/mnews/article/031/0001027735?sid=100",
        "description": "일본은 전체 원유의 93%를, 한국은 원유의 69%를 호르무즈해협을 통해 들여오고 있다. 또한 현재 호르무즈 해협 내에 발이 묶여 있는 양국 선박의 안전 문제와 통항 자유를 위한 국제적 공조 움직임에 동참하는 방안도 함께... ",
        "pubDate": "Mon, 11 May 2026 14:55:00 +0900",
        "formatted_date": "05월 11일, 14시 55분",
        "ai_summary": "한국과 일본이 호르무즈 해협의 선박 안전과 에너지 공급망 협력을 위해 안동 방문을 조율 중입니다.\n양국은 원유 수입 의존도가 높은 만큼 해협 통항 자유를 위한 공조 방안을 모색하고 있습니다."
      },
      {
        "title": "민주 '확장' 국힘 '사수'...호르무즈 피습 공세에 &quot;아마추어적&quot; 반발",
        "originallink": "https://www.ytn.co.kr/_ln/0101_202605111447095349",
        "link": "https://n.news.naver.com/mnews/article/052/0002351456?sid=004",
        "description": "민주당 소속 외통위원들은 기자회견을 열고 공세에만 혈안이 된 국민의힘의 처사는 오히려 호르무즈 해협에 있는 우리 선박 26척을 위협하는 아마추어적 행동이라고 꼬집었습니다. 야당이 요구한 상임위 질의에 대해선... ",
        "pubDate": "Mon, 11 May 2026 14:47:00 +0900",
        "formatted_date": "05월 11일, 14시 47분",
        "ai_summary": "민주당이 호르무즈 해협 관련 공세를 펴는 국민의힘을 향해 아마추어적 처사라며 강하게 비판했습니다.\n야당의 상임위 질의 요구에 대해 정부 대응을 방해하는 행위라고 맞서고 있습니다."
      },
      {
        "title": "국민의힘, 호르무즈 피격 관련 상임위 현안질의 요구… &quot;정부 강력 대응...",
        "originallink": "http://www.lawissue.co.kr/view.php?ud=202605111441417205b3279dfb36_12",
        "link": "http://www.lawissue.co.kr/view.php?ud=202605111441417205b3279dfb36_12",
        "description": "국민의힘이 11일 호르무즈 해협 한국 선박(나무호) 피격 사건과 관련해 국방위원회와 외교통일위원회 등 관련... 앞서 전날 정부는 지난 4일 호르무즈 해협에서 일어난 나무호 피격 사건은 미상 비행체의 타격에서... ",
        "pubDate": "Mon, 11 May 2026 14:44:00 +0900",
        "formatted_date": "05월 11일, 14시 44분",
        "ai_summary": "국민의힘이 호르무즈 해협 내 나무호 피격 사건과 관련해 정부의 강력한 대응을 촉구하며 상임위 현안질의를 요구했습니다.\n정부는 해당 사건이 미상 비행체에 의한 타격으로 확인되었다고 밝혔습니다."
      },
      {
        "title": "호르무즈 韓선박 안전 우려 확산 … 해운업계, 비용 급증에 '비명'",
        "originallink": "https://biz.newdaily.co.kr/site/data/html/2026/05/11/2026051100108.html",
        "link": "https://biz.newdaily.co.kr/site/data/html/2026/05/11/2026051100108.html",
        "description": "뉴데일리 이미현 기자 = 호르무즈 해협에 발이 묶인 한국 선박 25척의 선원 안전 우려가 커지고 있다. HMM... 호르무즈 해협에 갇힌 한국 선박 선원들의 하선 여부에도 관심이 쏠리고 있다. 선박은 법적으로 최소 안전운항... ",
        "pubDate": "Mon, 11 May 2026 14:34:00 +0900",
        "formatted_date": "05월 11일, 14시 34분",
        "ai_summary": "호르무즈 해협에 발이 묶인 한국 선박 25척의 선원 안전 문제가 심각해지고 있습니다.\n해운업계는 운항 차질에 따른 비용 급증과 선원 하선 문제로 깊은 우려를 표하고 있습니다."
      },
      {
        "title": "&quot;지금 사야 싸다&quot;…유럽내 항공권, 호르무즈 봉쇄에 최대 44% 급락",
        "originallink": "https://www.newsis.com/view/NISX20260511_0003624449",
        "link": "https://n.news.naver.com/mnews/article/003/0013937418?sid=104",
        "description": "이란 전쟁 여파로 호르무즈 해협 봉쇄가 3개월째 이어지며 항공유 부족 우려가 커지자, 불안을 느낀... 유럽은 아시아만큼 호르무즈 해협 경유 항공유 수입 의존도가 높지 않지만, 현재 미국산 공급에 상당 부분 기대고... ",
        "pubDate": "Mon, 11 May 2026 14:34:00 +0900",
        "formatted_date": "05월 11일, 14시 34분",
        "ai_summary": "호르무즈 해협 봉쇄로 인한 항공유 부족 우려가 커지며 유럽 내 항공권 가격이 급락했습니다.\n해협을 경유하는 에너지 공급 경로가 차단되면서 시장의 불안감이 반영된 결과입니다."
      },
      {
        "title": "나프타 6만 톤 싣고 호르무즈 탈출 선박 여수 입항",
        "originallink": "https://www.ytn.co.kr/_ln/0115_202605111425468233",
        "link": "https://n.news.naver.com/mnews/article/052/0002351438?sid=102",
        "description": "지난달 18일, 호르무즈 해협을 탈출한 석유제품 운반선이 여수에 도착했습니다. '내비게이트 맥앨리스터호... 지난달 호르무즈 해협을 탈출한 배가 오늘 오전 여수에 입항했다고요? [기자] 네 그렇습니다. 지금 제 뒤로... ",
        "pubDate": "Mon, 11 May 2026 14:25:00 +0900",
        "formatted_date": "05월 11일, 14시 25분",
        "ai_summary": "나프타 6만 톤을 실은 석유제품 운반선 네비게이트 맥앨리스터호가 호르무즈 해협을 탈출해 여수에 입항했습니다.\n위험 구역을 무사히 벗어난 선박이 국내로 안전하게 복귀했습니다."
      },
      {
        "title": "日다카이치 &quot;모든 선박 호르무즈 통과 위해 적극 조정할 것&quot;",
        "originallink": "https://www.newsis.com/view/NISX20260511_0003624256",
        "link": "https://n.news.naver.com/mnews/article/003/0013937325?sid=104",
        "description": "조기 호르무즈 해협 통과 실현을 위해 모든 외교적 노력과 조정을 적극적으로 계속하겠다&quot;고 밝혔다.... 운반선이 호르무즈 해협을 통과했다. 상선미쓰이 관련 기업이 보유한 인도 선적 액화석유가스(LPG) 운반선도 2척이... ",
        "pubDate": "Mon, 11 May 2026 14:15:00 +0900",
        "formatted_date": "05월 11일, 14시 15분",
        "ai_summary": "다카이치 일본 정무관이 모든 선박의 호르무즈 해협 통과를 위해 외교적 노력을 다하겠다고 밝혔습니다.\n현재 일본 관련 선박들이 해협을 통과하는 등 긴장을 완화하기 위한 조정이 진행 중입니다."
      },
      {
        "title": "나프타 5만5000톤 싣고 호르무즈 탈출한 맥앨리스터호, 여수 입항",
        "originallink": "https://www.news1.kr/local/gwangju-jeonnam/6162730",
        "link": "https://n.news.naver.com/mnews/article/421/0008937343?sid=102",
        "description": "나프타 5만 5000여톤을 싣고 호르무즈 해협을 탈출한 '네비게이트 맥앨리스터호'가 여수에 도착했다. 11일 업계에 따르면 지난달 18일 호르무즈 해협을 벗어난 맥앨리스터호가 이날 오전 11시 40분쯤 여수 사포2부두에... ",
        "pubDate": "Mon, 11 May 2026 14:01:00 +0900",
        "formatted_date": "05월 11일, 14시 01분",
        "ai_summary": "나프타 5만 5,000톤을 실은 네비게이트 맥앨리스터호가 호르무즈 해협을 탈출하여 여수 사포2부두에 도착했습니다.\n지난달 18일 해협을 벗어난 이후 정상적인 운항을 마치고 입항을 완료했습니다."
      },
      {
        "title": "국민의힘 &quot;정부, 호르무즈 피격 은폐&quot;‥상임위 현안질의 요구",
        "originallink": "https://imnews.imbc.com/news/2026/politics/article/6821485_36911.html",
        "link": "https://n.news.naver.com/mnews/article/214/0001498113?sid=100",
        "description": "국민의힘 소속 국회 외교통일위원회와 국방위원회 위원들이 호르무즈 해협 인근에서 발생한 나무호 폭발·화재 사건과 관련해 정부가 사실을 은폐했다며 상임위원회 개최를 요구했습니다. 국민의힘 외통위 위원들은 오늘... ",
        "pubDate": "Mon, 11 May 2026 14:00:00 +0900",
        "formatted_date": "05월 11일, 14시 00분",
        "ai_summary": "국민의힘이 정부가 호르무즈 해협 내 나무호 피격 사실을 은폐했다며 국회 상임위 현안질의를 강하게 요구했습니다.\n사건의 진상을 규명하고 정부의 투명한 정보 공개를 압박하는 모습입니다."
      },
      {
        "title": "호르무즈해협 탈출한 맥앨리스터호, 여수 사포2부두 입항",
        "originallink": "https://www.news1.kr/photos/7899273",
        "link": "https://n.news.naver.com/mnews/article/421/0008937312?sid=102",
        "description": "지난달 18일 호르무즈해협을 탈출한 '내비게이터 맥앨리스터호'가 11일 전남 여수 사포2부두에 입항하고 있다. 해당 선박에는 약 6만톤 규모의 나프타가 선적됐을 것으로 추정된다. (독자 제공. 재판매 및 DB금지)... ",
        "pubDate": "Mon, 11 May 2026 13:54:00 +0900",
        "formatted_date": "05월 11일, 13시 54분",
        "ai_summary": "호르무즈해협을 탈출한 '내비게이터 맥앨리스터호'가 나프타 6만톤을 싣고 여수 사포2부두에 입항했습니다."
      }
    ],
    "트럼프": [
      {
        "title": "트럼프발 관세 환급… 수출기업 2분기 ‘역대급’ 순이익 예고",
        "originallink": "https://www.asiatime.co.kr/article/20260511500274",
        "link": "https://www.asiatime.co.kr/article/20260511500274",
        "description": "2조·삼성 4조 등 환급 기대감↑ 트럼프 항소 변수… 전문가 “단기 호재보다 경쟁력 강화 집중해야” [아시아타임즈=이하영 기자] 미국 도널드 트럼프 2기 행정부의 ‘글로벌 관세 압박’이 사법부에서 부적절하다고... ",
        "pubDate": "Mon, 11 May 2026 14:58:00 +0900",
        "formatted_date": "05월 11일, 14시 58분",
        "ai_summary": "트럼프 행정부의 관세 정책 변화로 인한 환급 기대감에 국내 수출 기업들의 2분기 순이익이 크게 증가할 전망입니다. 전문가들은 단기적 호재보다 기업 자체 경쟁력 강화가 중요하다고 조언했습니다."
      },
      {
        "title": "트럼프 &quot;이란 2주 더 공격 가능&quot;…종전 협상 다시 흔들",
        "originallink": "https://www.nocutnews.co.kr/news/6515174?utm_source=naver&utm_medium=article&utm_campaign=20260511025556",
        "link": "https://n.news.naver.com/mnews/article/079/0004145546?sid=104",
        "description": "도널드 트럼프 미국 대통령이 이란을 2주간 더 공격할 수 있다고 말해 휴전협상이 흔들리고 있다. 트럼프 대통령은 10일(현지시간) 공개된 미 시사 프로그램 '풀 메저(Full Measure)' 인터뷰에서 지난 주말 종전 협상 결렬과... ",
        "pubDate": "Mon, 11 May 2026 14:56:00 +0900",
        "formatted_date": "05월 11일, 14시 56분",
        "ai_summary": "트럼프 대통령이 이란에 대한 2주간의 추가 공격 가능성을 시사하면서 중단되었던 종전 협상이 다시 난항을 겪고 있습니다."
      },
      {
        "title": "인민은행, 트럼프 방중 앞두고 위안가치 3년래 최고로 고시",
        "originallink": "https://www.newspim.com/news/view/20260511000937",
        "link": "https://www.newspim.com/news/view/20260511000937",
        "description": "중국 인민은행이 도널드 트럼프 미국 대통령 맞이에 나섰다. 인민은행은 11일 달러/위안 기준환율을 3년래 최저 수준으로, 즉 달러 대비 위안 가치를 3년만에 최고 수준으로 고시했다. 위안 환율에 대한 미국의... ",
        "pubDate": "Mon, 11 May 2026 14:54:00 +0900",
        "formatted_date": "05월 11일, 14시 54분",
        "ai_summary": "중국 인민은행이 트럼프 대통령의 방중을 앞두고 달러 대비 위안화 가치를 3년 만에 최고 수준으로 고시했습니다."
      },
      {
        "title": "[르포] 호텔앞 도로변 순찰차 20대…트럼프 방중 앞둔 베이징 곳곳 긴장...",
        "originallink": "https://www.yna.co.kr/view/AKR20260511093500083?input=1195m",
        "link": "https://n.news.naver.com/mnews/article/001/0016069877?sid=104",
        "description": "美대사관 인근 '트럼프 숙소 추정' 고급호텔은 객실 예약 중단 겉으로 보기에는 아직 평온…일각선 조용히 거대 이벤트 준비 한종구 특파원 = 도널드 트럼프 미국 대통령의 중국 방문이 이틀 앞으로 다가온 11일 오전... ",
        "pubDate": "Mon, 11 May 2026 14:54:00 +0900",
        "formatted_date": "05월 11일, 14시 54분",
        "ai_summary": "트럼프 대통령의 중국 방문을 이틀 앞두고 베이징은 숙소 인근 통제 등 철저한 경비 태세를 갖추며 긴장감이 고조되고 있습니다."
      },
      {
        "title": "&quot;트럼프 만족 위한 협상 아냐&quot;...핵 양보 생각 없는 이란, 농축 우라늄 ...",
        "originallink": "https://news.jtbc.co.kr/article/NB12297744?influxDiv=NAVER",
        "link": "https://n.news.naver.com/mnews/article/437/0000490863?sid=104",
        "description": "트럼프 대통령이 &quot;완전히 용납할 수없다&quot;고 밝혔습니다. 미국은 우라늄 농축을 이란이 20년간 유예하는 것과 호르무즈 해협에서의 자유로운 통항 보장 등을 핵심 조건으로 제시한 것으로 알려졌습니다. 이란 측은 &quot;트럼프... ",
        "pubDate": "Mon, 11 May 2026 14:49:00 +0900",
        "formatted_date": "05월 11일, 14시 49분",
        "ai_summary": "이란이 우라늄 농축 유예 등 미국의 핵심 요구 조건을 거부하며 핵 협상에 대한 강경한 태도를 유지하고 있습니다."
      },
      {
        "title": "트럼프, 불길에 휩싸인 드론 사진을 SNS에...고스란히 드러난 '초조함' ...",
        "originallink": "https://www.ytn.co.kr/_ln/0134_202605111447001086",
        "link": "https://n.news.naver.com/mnews/article/052/0002351451?sid=104",
        "description": "않고 트럼프 미국 대통령의 마음이 상당히 조급합니다. 그래서 일까요? 지난 주말 사이에 SNS에 AI 합성... 단순히 압박용인지 아니면 트럼프 대통령의 초조함을 드러낸 건지,화면 보시면서 직접 판단해보시면 좋을 것... ",
        "pubDate": "Mon, 11 May 2026 14:47:00 +0900",
        "formatted_date": "05월 11일, 14시 47분",
        "ai_summary": "트럼프 대통령이 SNS에 불타는 드론 합성 사진을 올린 것을 두고, 이란에 대한 압박 의도와 함께 그의 초조함이 드러난 것이라는 분석이 나옵니다."
      },
      {
        "title": "트럼프 &quot;2주간 더 이란 공격할 수도‥목표물 더 있어&quot;",
        "originallink": "https://imnews.imbc.com/news/2026/world/article/6821502_36925.html",
        "link": "https://n.news.naver.com/mnews/article/214/0001498130?sid=104",
        "description": "미국과 이란의 종전 협상이 다시 결렬된 가운데 도널드 트럼프 대통령이 이란을 2주간 더 공격할 수 있다고 발언한 인터뷰가 공개됐습니다. 트럼프 대통령은 현지시간 10일 공개된 미국 시사 프로그램 '풀 메저(Full Measure)... ",
        "pubDate": "Mon, 11 May 2026 14:47:00 +0900",
        "formatted_date": "05월 11일, 14시 47분",
        "ai_summary": "트럼프 대통령이 인터뷰를 통해 이란 내 추가 목표물을 겨냥한 2주간의 군사 작전 가능성을 언급했습니다."
      },
      {
        "title": "보석된 전광훈, '출국금지 해제' 소송…&quot;트럼프 만나러 미국 갈 것&quot;",
        "originallink": "https://www.sidae.com/article/2026051114180567737",
        "link": "https://n.news.naver.com/mnews/article/417/0001142597?sid=102",
        "description": "앞서 지난 10일 전 목사는 화상 설교에서 &quot;난 지금 출국금지가 돼 있으니 재판부에 요청해 2주만 미국 좀 보내달라고 허락받을 것&quot;이라며 &quot;도널드 트럼프 대통령을 키워낸 폴라 화이트 목사를 만나면 트럼프는 자동으로 만날... ",
        "pubDate": "Mon, 11 May 2026 14:46:00 +0900",
        "formatted_date": "05월 11일, 14시 46분",
        "ai_summary": "보석 상태인 전광훈 목사가 트럼프 대통령을 만나기 위해 출국금지 해제 소송을 진행하겠다고 밝혔습니다."
      },
      {
        "title": "[뉴스특보] 트럼프 '2주 추가 타격' 예고에 다시 긴장 고조",
        "originallink": "http://www.yonhapnewstv.co.kr/news/MYH20260511144356ZAQ",
        "link": "https://n.news.naver.com/mnews/article/422/0000863531?sid=104",
        "description": "미국과 이란의 종전 협상이 다시 좌초될 위기에 놓인 가운데, 트럼프 대통령이 “2주간 더 이란을 공격할... &lt;질문 1&gt; 종전 협상이 또 한 번 결렬된 가운데 트럼프 대통령이 추가 군사 공격 가능성을 언급한 인터뷰가... ",
        "pubDate": "Mon, 11 May 2026 14:45:00 +0900",
        "formatted_date": "05월 11일, 14시 45분",
        "ai_summary": "미국과 이란의 종전 협상이 결렬된 가운데, 트럼프 대통령의 추가 타격 예고로 인해 양국 간 긴장이 다시 최고조에 달하고 있습니다."
      },
      {
        "title": "트럼프 행정부, 이민자 시민권 박탈 ‘강행’",
        "originallink": "http://www.koreatimes.com/article/1612816",
        "link": "http://www.koreatimes.com/article/1612816",
        "description": "이번 조치는 트럼프 행정부가 추진 중인 강경 이민정책의 연장선으로, 시민권 취득 이후라도 허위 진술이... 트럼프 행정부는 이들이 애초 시민권 취득 자격이 없었으며, “중대한 사실 은폐 또는 고의적 허위 진술을... ",
        "pubDate": "Mon, 11 May 2026 14:42:00 +0900",
        "formatted_date": "05월 11일, 14시 42분",
        "ai_summary": "트럼프 행정부가 허위 진술 등을 이유로 시민권 취득자들의 시민권 박탈을 강행하고 있다. 이는 강경 이민정책의 일환으로 중대한 사실 은폐를 근거로 삼고 있다."
      }
    ],
    "유가": [
      {
        "title": "‘고유가 지원금’ 2차 18일부터 지급...2년전 소득으로 선별",
        "originallink": "https://www.cjb.co.kr/home/sub.php?menukey=61&mod=view&P_NO=260511504&PRO_CODE=99",
        "link": "https://n.news.naver.com/mnews/article/655/0000030920?sid=102",
        "description": "정부가 오는 18일부터 '2차 고유가 피해지원금' 신청을 받습니다. 11일 행정안전부에 따르면 2차 고유가 지원금은 2026년 3월 부과된 건강보험료를 기준으로 대상자를 선별합니다. 이는 2024년 소득을 기준으로 산정됐기... ",
        "pubDate": "Mon, 11 May 2026 14:58:00 +0900",
        "formatted_date": "05월 11일, 14시 58분",
        "ai_summary": "정부가 오는 18일부터 2차 고유가 피해지원금 신청을 받는다. 2026년 3월 기준 건강보험료를 바탕으로 대상자를 선별할 예정이다."
      },
      {
        "title": "국제유가, 美ㆍ이란 종전협상 교착 장기화 우려에 4% 넘게 급등",
        "originallink": "https://www.getnews.co.kr/news/articleView.html?idxno=869822",
        "link": "https://www.getnews.co.kr/news/articleView.html?idxno=869822",
        "description": "국제유가가 이번주들어서도 오름세를 나타냈다. 상승률도 4% 넘게 치솟았다. 역시 중동 리스크 확대... 단기적인 유가 상승 압력을 키우고 있다고 지적했다. 씨티그룹은 향후 3개월 내 브렌트유 전망치를 배럴당... ",
        "pubDate": "Mon, 11 May 2026 14:58:00 +0900",
        "formatted_date": "05월 11일, 14시 58분",
        "ai_summary": "미국과 이란 간의 종전 협상이 교착 상태에 빠지면서 중동 리스크 확대로 국제유가가 4% 이상 급등했다. 향후 유가 상승 압력이 지속될 전망이다."
      },
      {
        "title": "&quot;비행기 띄울수록 손해&quot; LCC, 고유가·고환율에 '무급휴직' 카드 꺼냈다",
        "originallink": "https://www.thepublic.kr/news/articleView.html?idxno=303938",
        "link": "https://www.thepublic.kr/news/articleView.html?idxno=303938",
        "description": "고유가·고환율로 운항 비용이 급증하자 인력 운용까지 조정하는 것이다. 11일 항공업계에 따르면... 항공업계에서는 고유가, 고환율이 이어질 경우 LCC들의 비용 절감 조치가 확대될 수 있다고 보고 있다. 업계... ",
        "pubDate": "Mon, 11 May 2026 14:58:00 +0900",
        "formatted_date": "05월 11일, 14시 58분",
        "ai_summary": "고유가와 고환율로 운항 비용이 급증한 저비용항공사(LCC)들이 경영난을 겪고 있다. 비용 절감을 위해 무급휴직 등 인력 조정 카드를 꺼내 들었다."
      },
      {
        "title": "고유가 장기화 시 소비자물가 1.6%p 추가 상승 가능",
        "originallink": "https://www.kgnews.co.kr/news/article.html?no=895203",
        "link": "https://www.kgnews.co.kr/news/article.html?no=895203",
        "description": "한국개발연구원(KDI)은 국제유가 상승 특히 운송 불확실성으로 인한 고유가 장기화 상황에서 올해 소비자물가 상승률이 최대 1.6%포인트(p) 추가 상승할 수 있다고 분석했다. 마창석 KDI 경제전망실 연구위원은 11일... ",
        "pubDate": "Mon, 11 May 2026 14:58:00 +0900",
        "formatted_date": "05월 11일, 14시 58분",
        "ai_summary": "KDI는 고유가 상황이 장기화될 경우 올해 소비자물가 상승률이 최대 1.6%포인트 추가 상승할 수 있다고 분석했다. 운송 불확실성이 물가 상승을 부추기는 요인이다."
      },
      {
        "title": "고유가 장기화 시 올해 물가 최대 1.6%p 더 오른다",
        "originallink": "https://www.joongangenews.com/news/articleView.html?idxno=518353",
        "link": "https://www.joongangenews.com/news/articleView.html?idxno=518353",
        "description": "고유가가 장기화될 경우 올해 소비자물가 상승률이 최대 1.6%포인트(p) 추가 상승할 수 있다는 분석을 내놨다. [사진=연합뉴스]  국책연구기관인 한국개발연구원(KDI)이 고유가가 장기화될 경우 올해 소비자물가... ",
        "pubDate": "Mon, 11 May 2026 14:56:00 +0900",
        "formatted_date": "05월 11일, 14시 56분",
        "ai_summary": "KDI는 고유가 장기화 시 올해 소비자물가가 최대 1.6%p 추가 상승할 수 있다고 전망했다. 유가 상승이 물가에 미치는 영향이 상당할 것으로 보인다."
      },
      {
        "title": "고유가 피해지원금 2차 지급 18일 시작…소득 하위 70%에 최대 25만 원",
        "originallink": "http://www.chungnamilbo.co.kr/news/articleView.html?idxno=887760",
        "link": "http://www.chungnamilbo.co.kr/news/articleView.html?idxno=887760",
        "description": "정부가 고유가·고물가 부담 완화를 위한 '고유가 피해지원금' 2차 지급에 나선다. 지원 대상은 소득 하위 70% 국민으로, 지역에 따라 10만~25만 원이 차등 지급된다. (사진제공=연합뉴스)  정부가 고유가·고물가 부담... ",
        "pubDate": "Mon, 11 May 2026 14:56:00 +0900",
        "formatted_date": "05월 11일, 14시 56분",
        "ai_summary": "정부가 고유가 부담 완화를 위해 2차 피해지원금을 지급한다. 소득 하위 70% 국민을 대상으로 지역에 따라 10만 원에서 25만 원을 차등 지급한다."
      },
      {
        "title": "고유가 피해지원금 방문 신청 도와 드려요",
        "originallink": "http://www.dynews.co.kr/news/articleView.html?idxno=849762",
        "link": "http://www.dynews.co.kr/news/articleView.html?idxno=849762",
        "description": "［동양일보 심영선 기자］ 음성군 생극면이 고유가 피해지원금 신청에 어려움을 겪는 고령자와 장애인을 대상으로 찾아가는 신청 서비스를 지원한다. 생극면은 피해지원금 적기 지급을 위해 병원과 노인 생활 시설... ",
        "pubDate": "Mon, 11 May 2026 14:54:00 +0900",
        "formatted_date": "05월 11일, 14시 54분",
        "ai_summary": "음성군 생극면이 고유가 피해지원금 신청이 어려운 고령자와 장애인을 위해 찾아가는 서비스를 제공한다. 행정 사각지대를 해소하기 위한 조치다."
      },
      {
        "title": "미국·이란 종전 협상 교착…국제유가 3%대 상승",
        "originallink": "https://www.fntoday.co.kr/news/articleView.html?idxno=384139",
        "link": "https://www.fntoday.co.kr/news/articleView.html?idxno=384139",
        "description": "미국과 이란 간 종전 협상이 교착 국면에 빠질 수 있다는 우려가 커지면서 국제유가가 3%대 상승세를... 이에 따라 종전 협상 타결 기대감이 위축되면서 유가 상승 압력이 커진 것으로 풀이된다. 씨티그룹은... ",
        "pubDate": "Mon, 11 May 2026 14:54:00 +0900",
        "formatted_date": "05월 11일, 14시 54분",
        "ai_summary": "미국과 이란의 종전 협상 지연 우려로 국제유가가 3%대 상승했다. 협상 타결 기대감이 줄어들며 유가 상승 압력이 커지고 있다."
      },
      {
        "title": "에쓰오일, 1분기 영업이익 1조2311억 … 고유가·재고효과에 '깜짝 실적...",
        "originallink": "http://www.worktoday.co.kr/news/articleView.html?idxno=84481",
        "link": "http://www.worktoday.co.kr/news/articleView.html?idxno=84481",
        "description": "시행에도 유가 상승에 따른 재고 평가이익에 힘입어 1조 원대 영업이익을 기록했다. 다만 실적의 상당 부분이 일회성 요인에 기반한 만큼 향후 유가 변동에 따른 실적 변동성 확대가 변수로 지목된다. 에쓰오일은... ",
        "pubDate": "Mon, 11 May 2026 14:54:00 +0900",
        "formatted_date": "05월 11일, 14시 54분",
        "ai_summary": "에쓰오일이 고유가에 따른 재고 평가이익 덕분에 1분기 1조 원대 영업이익을 기록했다. 다만 일회성 요인으로 인한 향후 실적 변동성 확대가 우려된다."
      },
      {
        "title": "고유가 지원금 2차 지급 시작…연봉 1억 외벌이 4인 가구는 100만원",
        "originallink": "https://www.ezyeconomy.com/news/articleView.html?idxno=235325",
        "link": "https://www.ezyeconomy.com/news/articleView.html?idxno=235325",
        "description": "오는 18일부터 취약계층을 제외한 소득 하위 70% 국민을 대상으로 1인당 10만~25만원의 '고유가 피해지원금' 2차 지급이 시작된다. 신청과 지급은 7월 3일까지 진행된다. 정부는 앞서 지난달 27일부터 차상위계층 등... ",
        "pubDate": "Mon, 11 May 2026 14:54:00 +0900",
        "formatted_date": "05월 11일, 14시 54분",
        "ai_summary": "18일부터 소득 하위 70% 국민을 대상으로 2차 고유가 피해지원금 지급이 시작된다. 지원금은 1인당 10만~25만 원이며 7월 3일까지 신청 및 지급된다."
      }
    ],
    "코스피": [
      {
        "title": "[이슈] 코스피 7000 돌파했지만…한국 잠재성장률은 역대 최저 전망",
        "originallink": "https://www.polinews.co.kr/news/articleView.html?idxno=730777",
        "link": "https://www.polinews.co.kr/news/articleView.html?idxno=730777",
        "description": "코스피가 사상 처음으로 7000선을 돌파하며 국내 증시가 활황을 이어가고 있지만 한국 경제의 기초 체력은 오히려 약화하고 있다는 경고음이 커지고 있다. 경제협력개발기구는 한국의 내년 잠재성장률이 역대 최저... ",
        "pubDate": "Mon, 11 May 2026 14:54:00 +0900",
        "formatted_date": "05월 11일, 14시 54분",
        "ai_summary": "코스피가 사상 처음 7000선을 돌파하며 활황을 보이고 있으나, 한국 경제의 잠재성장률은 역대 최저 수준으로 떨어질 것이라는 우려가 제기된다."
      },
      {
        "title": "'7899.32' 기록한 코스피 [포토]",
        "originallink": "https://news.tf.co.kr/read/photomovie/2321328.htm",
        "link": "https://n.news.naver.com/mnews/article/629/0000498106?sid=101",
        "description": "코스피가 사상 최초로 장중 7899.32를 기록한 11일 오후 서울 중구 하나은행 본점 딜링룸에 코스피가 표시돼 있다. 이날 7775.31에 거래를 시작한 코스피는 오전 9시 2분께 전 거래일 대비 418.66포인트(4.25%) 오른... ",
        "pubDate": "Mon, 11 May 2026 14:53:00 +0900",
        "formatted_date": "05월 11일, 14시 53분",
        "ai_summary": "코스피 지수가 사상 최초로 장중 7899.32를 기록하며 역대 최고치를 경신하는 등 강한 상승세를 보였다."
      },
      {
        "title": "[이슈] 코스피 7000 돌파에 보험 해지 급증…증시로 자금 이동 확산",
        "originallink": "https://www.polinews.co.kr/news/articleView.html?idxno=730772",
        "link": "https://www.polinews.co.kr/news/articleView.html?idxno=730772",
        "description": "코스피가 사상 처음으로 7000선을 돌파하며 증시 활황이 이어지는 가운데 보험상품을 해지해 주식 투자... 실제 코스피는 지난해 10월 처음으로 4000선을 돌파한 이후 상승세를 이어가며 지난 6일 사상 처음으로 7000선을... ",
        "pubDate": "Mon, 11 May 2026 14:53:00 +0900",
        "formatted_date": "05월 11일, 14시 53분",
        "ai_summary": "코스피 7000 돌파로 주식 시장이 과열되면서 보험을 해지해 주식 투자에 뛰어드는 자금 이동 현상이 확산하고 있다."
      },
      {
        "title": "거침없는 코스피, 어디까지 가나",
        "originallink": "https://www.bigtanews.co.kr/article/view/big202605110006",
        "link": "https://www.bigtanews.co.kr/article/view/big202605110006",
        "description": "빅터뉴스 이재영 기자 코스피가 11일 또 한 번 역사를 새로 썼다. 국내 증시 시가총액이 사상 처음으로... 이날 오전 10시 8분 기준 코스피와 코스닥 합산 시가총액은 7037조7977억원으로 집계됐다. 코스피 단독으로는... ",
        "pubDate": "Mon, 11 May 2026 14:52:00 +0900",
        "formatted_date": "05월 11일, 14시 52분",
        "ai_summary": "코스피와 코스닥 합산 시가총액이 7037조 원을 넘어서며 국내 증시가 연일 새로운 역사를 쓰고 있다."
      },
      {
        "title": "BNK부산은행, 코스피200 지수연동 예금… 연최고 4.3% 기대",
        "originallink": "https://www.g-enews.com/view.php?ud=20260511143319585cd0bfacc1c_1",
        "link": "https://www.g-enews.com/view.php?ud=20260511143319585cd0bfacc1c_1",
        "description": "BNK부산은행이 코스피200 지수 성과에 따라 추가 수익을 제공하는 지수연동형 예금 상품 판매에 나선다. 부산은행은 최고 연 4.3% 수익률을 기대할 수 있는 'BNK지수연동 정기예금 3차'를 출시했다고 11일 밝혔다.... ",
        "pubDate": "Mon, 11 May 2026 14:48:00 +0900",
        "formatted_date": "05월 11일, 14시 48분",
        "ai_summary": "BNK부산은행이 코스피200 지수 성과와 연동해 최고 연 4.3% 수익을 기대할 수 있는 지수연동형 정기예금 상품을 출시했다."
      },
      {
        "title": "'1만피' 시대 오나…JP모건 &quot;AI 모멘텀 올라탄 韓증시, 코스피 1만도 가...",
        "originallink": "https://www.ajunews.com/view/20260511144158230",
        "link": "https://www.ajunews.com/view/20260511144158230",
        "description": "아주경제=양보연 기자 byeony@ajunews.com 11일 서울 중구 하나은행 딜링룸 현황판에 코스피 등이 표시되고 있다. 이날 코스피는 전 거래일 대비 277.31포인트(3.70%) 오른 7775.31에, 코스닥은 5.16포인트(0.43%) 오른 1212.88에... ",
        "pubDate": "Mon, 11 May 2026 14:48:00 +0900",
        "formatted_date": "05월 11일, 14시 48분",
        "ai_summary": "AI 산업 모멘텀을 바탕으로 코스피가 급등하자 JP모건 등 금융권에서 코스피 1만 포인트 돌파 가능성을 언급하고 있다."
      },
      {
        "title": "코스피 5.29% 상승 7894.28 거래중",
        "originallink": "https://www.newspim.com/news/view/20260511000919",
        "link": "https://www.newspim.com/news/view/20260511000919",
        "description": "11일 오후 코스피가 전장 종가보다 396.28 포인트(5.29%) 상승하며 7894.28로, 코스닥은 3.40 포인트(0.28%) 하락한 1204.32로 거래되는 가운데, 서울 중구 하나은행 을지로본점 딜링룸에서 직원들이 업무를 보고... ",
        "pubDate": "Mon, 11 May 2026 14:46:00 +0900",
        "formatted_date": "05월 11일, 14시 46분",
        "ai_summary": "코스피가 전 거래일 대비 5% 넘게 급등하며 7894선에서 거래되는 등 폭발적인 상승세를 기록 중이다."
      },
      {
        "title": "[기자의 눈] 코스피 8000, 한국 증시의 새 가격표",
        "originallink": "https://www.ekn.kr/web/view.php?key=20260511026013692",
        "link": "https://www.ekn.kr/web/view.php?key=20260511026013692",
        "description": "코스피 지수가 8000포인트를 눈앞에 두고 있다. 쉴 새 없이 오른 지수를 두고 과열이라는 우려와 버블 논쟁이... 코스피 7000은 단순한 주가 상승이 아니라, 오랫동안 한국 증시에 붙어 있던 할인율을 다시 계산하는 과정으로... ",
        "pubDate": "Mon, 11 May 2026 14:42:00 +0900",
        "formatted_date": "05월 11일, 14시 42분",
        "ai_summary": "코스피 8000 돌파가 가시화된 가운데, 이를 단순한 과열로 볼지 한국 증시의 가치 재평가로 볼지에 대한 시장의 논쟁이 뜨겁다."
      },
      {
        "title": "코스피, 7900선 눈앞에 둔 7880선…개인·기관 매수세 [fn오후시황]",
        "originallink": "http://www.fnnews.com/news/202605111436285486",
        "link": "https://n.news.naver.com/mnews/article/014/0005519739?sid=101",
        "description": "코스피가 11일 개인과 기관의 매수세에 7900선 돌파를 눈앞에 두고 있다. 이날 오후 2시 25분 코스피는 전 거래일 대비 385.43p(5.14%) 오른 7883.43에 거래되고 있다. 코스피는 이날 전장 대비 277.31p(3.70%) 오른... ",
        "pubDate": "Mon, 11 May 2026 14:38:00 +0900",
        "formatted_date": "05월 11일, 14시 38분",
        "ai_summary": "개인과 기관의 매수세가 이어지며 코스피가 7900선 돌파를 눈앞에 둔 7880선에서 거래되고 있다."
      },
      {
        "title": "코스피 7000 돌파에 보험해지 급증…'머니무브' 생보업계 강타",
        "originallink": "https://www.joongangenews.com/news/articleView.html?idxno=518338",
        "link": "https://www.joongangenews.com/news/articleView.html?idxno=518338",
        "description": "|중앙이코노미뉴스 정재혁 기자|코스피가 7000선을 돌파하며 증시로 자금이 이동하는 '머니무브' 현상이 보험업계까지 번지고 있다. [사진=구글 제미나이로 생성한 이미지]  코스피가 7000선을 돌파하며 증시로... ",
        "pubDate": "Mon, 11 May 2026 14:36:00 +0900",
        "formatted_date": "05월 11일, 14시 36분",
        "ai_summary": "코스피 7000선 돌파로 증시 활황이 이어지면서 보험을 해지하고 투자로 자금을 옮기는 '머니무브' 현상이 생명보험업계를 강타하고 있습니다."
      }
    ]
  },
  "last_updated": "2026-05-11 15:02:10"
}